[{"Artifacts":[{"Id":"4","RawArtifactId":"ClassicalNativeAmericanTomahawk","PositionX":22,"PositionY":6,"Slot":0,"Condition":"Decrepit","Rarity":"Common"},{"Id":"4","RawArtifactId":"ClassicalNativeAmericanTomahawk","PositionX":22,"PositionY":6,"Slot":0,"Condition":"Decrepit","Rarity":"Common"},{"Id":"tutorialArtifact","RawArtifactId":"ClassicalNativeAmericanTomahawk","PositionX":24,"PositionY":2,"Slot":4,"Condition":"Decrepit","Rarity":"Common"},{"Id":"tutorialArtifact","RawArtifactId":"ClassicalNativeAmericanTomahawk","PositionX":24,"PositionY":2,"Slot":4,"Condition":"Decrepit","Rarity":"Common"}]}]