[{"Artifacts":[{"Id":"4","RawArtifactId":"ClassicalNativeAmericanTomahawk","PositionX":22,"PositionY":6,"Slot":0},{"Id":"3","RawArtifactId":"MedievalNativeAmericanTomahawk","PositionX":24,"PositionY":2,"Slot":5},{"Id":"tutorialArtifact","RawArtifactId":"ClassicalNativeAmericanTomahawk","PositionX":24,"PositionY":2,"Slot":6},{"Id":"5","RawArtifactId":"AncientNativeAamericanClub","PositionX":6,"PositionY":14,"Slot":7},{"Id":"6","RawArtifactId":"ClassicalNativeAmericanWoodenSword","PositionX":17,"PositionY":13,"Slot":8}]}]