[{"Id":"a3593d27-2ded-4535-b775-9f02e683c1cd","ExhibitVariationName":"SmallWoodenExhibitBasic","XPosition":-17,"YPosition":-4,"RotationFrame":0,"ExhibitDecoration":"string","ExhibitArtifactSlot1":"","ExhibitArtifactSlot2":"string","ExhibitArtifactSlot3":"string","ExhibitArtifactSlot4":"string","ExhibitArtifactSlot5":"string"},{"Id":"89898734-e7b9-459b-b334-ca1d99b8d3d5","ExhibitVariationName":"LargeWoodenExhibitBasic","XPosition":-16,"YPosition":-10,"RotationFrame":0,"ExhibitDecoration":"string","ExhibitArtifactSlot1":"","ExhibitArtifactSlot2":"","ExhibitArtifactSlot3":"string","ExhibitArtifactSlot4":"string","ExhibitArtifactSlot5":"string"},{"Id":"16a9e1c6-01eb-4b0a-be59-b9189ca362e0","ExhibitVariationName":"LargeWoodenExhibitBasic","XPosition":-16,"YPosition":-16,"RotationFrame":0,"ExhibitDecoration":"string","ExhibitArtifactSlot1":"","ExhibitArtifactSlot2":"string","ExhibitArtifactSlot3":"string","ExhibitArtifactSlot4":"string","ExhibitArtifactSlot5":"string"}]