[{"Id":"a3593d27-2ded-4535-b775-9f02e683c1cd","ExhibitVariationName":"BasicExhibit1x1","XPosition":-17,"YPosition":-4,"RotationFrame":0,"ExhibitDecoration":"string","ExhibitArtifactSlot1":"","ExhibitArtifactSlot2":"string","ExhibitArtifactSlot3":"string","ExhibitArtifactSlot4":"string","ExhibitArtifactSlot5":"string"},{"Id":"0a325e7c-5410-4261-86aa-1a49d391c91c","ExhibitVariationName":"BasicExhibit1x1","XPosition":-17,"YPosition":-13,"RotationFrame":0,"ExhibitDecoration":"string","ExhibitArtifactSlot1":"string","ExhibitArtifactSlot2":"string","ExhibitArtifactSlot3":"string","ExhibitArtifactSlot4":"string","ExhibitArtifactSlot5":"string"},{"Id":"b947e912-1270-45ca-a3e3-4d5b7a358360","ExhibitVariationName":"BasicExhibit4x4","XPosition":-16,"YPosition":-18,"RotationFrame":0,"ExhibitDecoration":"string","ExhibitArtifactSlot1":"string","ExhibitArtifactSlot2":"string","ExhibitArtifactSlot3":"string","ExhibitArtifactSlot4":"string","ExhibitArtifactSlot5":"string"},{"Id":"fb46af0f-3716-4e4b-9739-c290f30378a3","ExhibitVariationName":"BasicExhibit1x1","XPosition":-12,"YPosition":-19,"RotationFrame":0,"ExhibitDecoration":"string","ExhibitArtifactSlot1":"string","ExhibitArtifactSlot2":"string","ExhibitArtifactSlot3":"string","ExhibitArtifactSlot4":"string","ExhibitArtifactSlot5":"string"}]