[{"Id":"fa07c992-d9fd-4c2a-8ef7-808b71851056","XPosition":0,"YPosition":0,"TileSetNumber":7,"TileAtlasCoOrdinateX":0,"TileAtlasCoOrdinateY":0,"Layer":0,"IsInZone":false,"WallId":"string","Walkable":false,"ExhibitId":"string","HangingLightId":"string"},{"Id":"ad760bad-acf6-4a81-8fa4-c09ffb256291","XPosition":0,"YPosition":-1,"TileSetNumber":7,"TileAtlasCoOrdinateX":0,"TileAtlasCoOrdinateY":0,"Layer":0,"IsInZone":false,"WallId":"string","Walkable":false,"ExhibitId":"string","HangingLightId":"string"},{"Id":"a5bc7ee9-5d56-43df-a3d9-eceae5c5f96d","XPosition":0,"YPosition":-2,"TileSetNumber":7,"TileAtlasCoOrdinateX":0,"TileAtlasCoOrdinateY":0,"Layer":0,"IsInZone":false,"WallId":"string","Walkable":false,"ExhibitId":"string","HangingLightId":"string"},{"Id":"e727867b-3499-4159-af74-1519e06a3767","XPosition":0,"YPosition":-3,"TileSetNumber":7,"TileAtlasCoOrdinateX":0,"TileAtlasCoOrdinateY":0,"Layer":0,"IsInZone":false,"WallId":"string","Walkable":false,"ExhibitId":"string","HangingLightId":"string"},{"Id":"acdd6f08-cd5c-4fef-8d74-6199219c7f48","XPosition":0,"YPosition":-4,"TileSetNumber":7,"TileAtlasCoOrdinateX":0,"TileAtlasCoOrdinateY":0,"Layer":0,"IsInZone":false,"WallId":"string","Walkable":false,"ExhibitId":"string","HangingLightId":"string"},{"Id":"098d2c9c-95e0-4287-a463-5a6209c6e5c7","XPosition":0,"YPosition":-5,"TileSetNumber":7,"TileAtlasCoOrdinateX":0,"TileAtlasCoOrdinateY":0,"Layer":0,"IsInZone":false,"WallId":"string","Walkable":false,"ExhibitId":"string","HangingLightId":"string"},{"Id":"926eb2a4-e376-4496-a3a8-2ed554d6dea2","XPosition":0,"YPosition":-6,"TileSetNumber":7,"TileAtlasCoOrdinateX":0,"TileAtlasCoOrdinateY":0,"Layer":0,"IsInZone":false,"WallId":"string","Walkable":false,"ExhibitId":"string","HangingLightId":"string"},{"Id":"b885b329-282f-45ec-aeb9-f03f6fe37dd3","XPosition":0,"YPosition":-7,"TileSetNumber":7,"TileAtlasCoOrdinateX":0,"TileAtlasCoOrdinateY":0,"Layer":0,"IsInZone":false,"WallId":"string","Walkable":true,"ExhibitId":"string","HangingLightId":"string"},{"Id":"b6969414-be81-4781-b443-f68cb4b91690","XPosition":0,"YPosition":-8,"TileSetNumber":7,"TileAtlasCoOrdinateX":0,"TileAtlasCoOrdinateY":0,"Layer":0,"IsInZone":false,"WallId":"string","Walkable":true,"ExhibitId":"string","HangingLightId":"string"},{"Id":"213f688f-1ef0-4a50-92ec-bcff17db2331","XPosition":0,"YPosition":-9,"TileSetNumber":7,"TileAtlasCoOrdinateX":0,"TileAtlasCoOrdinateY":0,"Layer":0,"IsInZone":false,"WallId":"string","Walkable":false,"ExhibitId":"string","HangingLightId":"string"},{"Id":"7c71c952-f67e-4f65-b115-acdf355c1293","XPosition":0,"YPosition":-10,"TileSetNumber":7,"TileAtlasCoOrdinateX":0,"TileAtlasCoOrdinateY":0,"Layer":0,"IsInZone":false,"WallId":"string","Walkable":false,"ExhibitId":"string","HangingLightId":"string"},{"Id":"e7b29914-6899-4041-bf1c-f547075cc19d","XPosition":0,"YPosition":-11,"TileSetNumber":7,"TileAtlasCoOrdinateX":0,"TileAtlasCoOrdinateY":0,"Layer":0,"IsInZone":false,"WallId":"string","Walkable":false,"ExhibitId":"string","HangingLightId":"string"},{"Id":"f177e48d-3c73-4c38-b9a8-298b8e5a84b6","XPosition":0,"YPosition":-12,"TileSetNumber":7,"TileAtlasCoOrdinateX":0,"TileAtlasCoOrdinateY":0,"Layer":0,"IsInZone":false,"WallId":"string","Walkable":false,"ExhibitId":"string","HangingLightId":"string"},{"Id":"9fc234f9-6766-49fd-9015-25d9ee45e96e","XPosition":0,"YPosition":-13,"TileSetNumber":7,"TileAtlasCoOrdinateX":0,"TileAtlasCoOrdinateY":0,"Layer":0,"IsInZone":false,"WallId":"string","Walkable":false,"ExhibitId":"string","HangingLightId":"string"},{"Id":"b5f041a8-3c3d-4680-a435-e275cb4e9437","XPosition":0,"YPosition":-14,"TileSetNumber":7,"TileAtlasCoOrdinateX":0,"TileAtlasCoOrdinateY":0,"Layer":0,"IsInZone":false,"WallId":"string","Walkable":false,"ExhibitId":"string","HangingLightId":"string"},{"Id":"924894e5-2839-4eba-9a2a-4f16fbe478f1","XPosition":0,"YPosition":-15,"TileSetNumber":7,"TileAtlasCoOrdinateX":0,"TileAtlasCoOrdinateY":0,"Layer":0,"IsInZone":false,"WallId":"string","Walkable":false,"ExhibitId":"string","HangingLightId":"string"},{"Id":"ca081c64-63e8-46da-8bb8-cff1cb48b4ac","XPosition":0,"YPosition":-16,"TileSetNumber":7,"TileAtlasCoOrdinateX":0,"TileAtlasCoOrdinateY":0,"Layer":0,"IsInZone":false,"WallId":"string","Walkable":false,"ExhibitId":"string","HangingLightId":"string"},{"Id":"5483de6f-a86d-47b6-845e-50ac47eebeb9","XPosition":0,"YPosition":-17,"TileSetNumber":7,"TileAtlasCoOrdinateX":0,"TileAtlasCoOrdinateY":0,"Layer":0,"IsInZone":false,"WallId":"string","Walkable":false,"ExhibitId":"string","HangingLightId":"string"},{"Id":"06960b1b-9c81-4ff1-b79e-37e099d04fbe","XPosition":0,"YPosition":-18,"TileSetNumber":7,"TileAtlasCoOrdinateX":0,"TileAtlasCoOrdinateY":0,"Layer":0,"IsInZone":false,"WallId":"string","Walkable":false,"ExhibitId":"string","HangingLightId":"string"},{"Id":"63734e4a-c9b4-4385-ab7e-ba8f67f59014","XPosition":0,"YPosition":-19,"TileSetNumber":7,"TileAtlasCoOrdinateX":0,"TileAtlasCoOrdinateY":0,"Layer":0,"IsInZone":false,"WallId":"basic_red_wallpaper","Walkable":false,"ExhibitId":"string","HangingLightId":"string"},{"Id":"31ad12e1-fdd6-4314-afe5-3fe68fed48af","XPosition":-1,"YPosition":0,"TileSetNumber":7,"TileAtlasCoOrdinateX":0,"TileAtlasCoOrdinateY":0,"Layer":0,"IsInZone":false,"WallId":"string","Walkable":false,"ExhibitId":"string","HangingLightId":"string"},{"Id":"3ffd27e5-bf01-45ec-b7e9-de861671b644","XPosition":-1,"YPosition":-1,"TileSetNumber":7,"TileAtlasCoOrdinateX":0,"TileAtlasCoOrdinateY":0,"Layer":0,"IsInZone":false,"WallId":"string","Walkable":true,"ExhibitId":"string","HangingLightId":"string"},{"Id":"ffe64c0c-7499-49b5-820b-a5476954c380","XPosition":-1,"YPosition":-2,"TileSetNumber":7,"TileAtlasCoOrdinateX":0,"TileAtlasCoOrdinateY":0,"Layer":0,"IsInZone":false,"WallId":"string","Walkable":true,"ExhibitId":"string","HangingLightId":"string"},{"Id":"72bf89d8-b96e-487e-a56a-c748d6c2b915","XPosition":-1,"YPosition":-3,"TileSetNumber":7,"TileAtlasCoOrdinateX":0,"TileAtlasCoOrdinateY":0,"Layer":0,"IsInZone":false,"WallId":"string","Walkable":true,"ExhibitId":"string","HangingLightId":"string"},{"Id":"28f6d979-6e68-45ed-92d2-5f4480a20564","XPosition":-1,"YPosition":-4,"TileSetNumber":7,"TileAtlasCoOrdinateX":0,"TileAtlasCoOrdinateY":0,"Layer":0,"IsInZone":false,"WallId":"string","Walkable":true,"ExhibitId":"string","HangingLightId":"string"},{"Id":"43c48920-9f17-4eb9-b226-5c785dde47cd","XPosition":-1,"YPosition":-5,"TileSetNumber":7,"TileAtlasCoOrdinateX":0,"TileAtlasCoOrdinateY":0,"Layer":0,"IsInZone":false,"WallId":"string","Walkable":true,"ExhibitId":"string","HangingLightId":"string"},{"Id":"56d97b41-45a8-4bab-ae8c-c90ff68b89b4","XPosition":-1,"YPosition":-6,"TileSetNumber":7,"TileAtlasCoOrdinateX":0,"TileAtlasCoOrdinateY":0,"Layer":0,"IsInZone":false,"WallId":"string","Walkable":true,"ExhibitId":"string","HangingLightId":"string"},{"Id":"83f0d76a-a36c-45c6-bf48-d4226e5bee2c","XPosition":-1,"YPosition":-7,"TileSetNumber":7,"TileAtlasCoOrdinateX":0,"TileAtlasCoOrdinateY":0,"Layer":0,"IsInZone":false,"WallId":"string","Walkable":true,"ExhibitId":"string","HangingLightId":"string"},{"Id":"36fc6ccd-26fc-4a39-b592-4eb23d48624e","XPosition":-1,"YPosition":-8,"TileSetNumber":7,"TileAtlasCoOrdinateX":0,"TileAtlasCoOrdinateY":0,"Layer":0,"IsInZone":false,"WallId":"string","Walkable":true,"ExhibitId":"string","HangingLightId":"string"},{"Id":"da23dc64-64a0-4c6d-b4cf-1db2651b09b1","XPosition":-1,"YPosition":-9,"TileSetNumber":7,"TileAtlasCoOrdinateX":0,"TileAtlasCoOrdinateY":0,"Layer":0,"IsInZone":false,"WallId":"string","Walkable":true,"ExhibitId":"string","HangingLightId":"string"},{"Id":"09ad9de7-3956-4837-8101-1c7d23331cdf","XPosition":-1,"YPosition":-10,"TileSetNumber":7,"TileAtlasCoOrdinateX":0,"TileAtlasCoOrdinateY":0,"Layer":0,"IsInZone":false,"WallId":"string","Walkable":true,"ExhibitId":"string","HangingLightId":"string"},{"Id":"a9f92326-07a1-40cf-9b18-4dbf5b33c273","XPosition":-1,"YPosition":-11,"TileSetNumber":7,"TileAtlasCoOrdinateX":0,"TileAtlasCoOrdinateY":0,"Layer":0,"IsInZone":false,"WallId":"string","Walkable":true,"ExhibitId":"string","HangingLightId":"string"},{"Id":"3837ccc3-05ea-4429-b0b5-f64cd2b1912e","XPosition":-1,"YPosition":-12,"TileSetNumber":7,"TileAtlasCoOrdinateX":0,"TileAtlasCoOrdinateY":0,"Layer":0,"IsInZone":false,"WallId":"string","Walkable":true,"ExhibitId":"string","HangingLightId":"string"},{"Id":"2c2855db-e78d-421d-ad56-617b7f9f80da","XPosition":-1,"YPosition":-13,"TileSetNumber":7,"TileAtlasCoOrdinateX":0,"TileAtlasCoOrdinateY":0,"Layer":0,"IsInZone":false,"WallId":"string","Walkable":true,"ExhibitId":"string","HangingLightId":"string"},{"Id":"a5a7f627-d122-4bff-8498-67cf2d0ea991","XPosition":-1,"YPosition":-14,"TileSetNumber":7,"TileAtlasCoOrdinateX":0,"TileAtlasCoOrdinateY":0,"Layer":0,"IsInZone":false,"WallId":"string","Walkable":true,"ExhibitId":"string","HangingLightId":"string"},{"Id":"5e65d727-f6e6-41c4-8c32-bf9ce8d76626","XPosition":-1,"YPosition":-15,"TileSetNumber":7,"TileAtlasCoOrdinateX":0,"TileAtlasCoOrdinateY":0,"Layer":0,"IsInZone":false,"WallId":"string","Walkable":true,"ExhibitId":"string","HangingLightId":"string"},{"Id":"496e8ae8-4e41-4a7b-9e77-5446ad964866","XPosition":-1,"YPosition":-16,"TileSetNumber":7,"TileAtlasCoOrdinateX":0,"TileAtlasCoOrdinateY":0,"Layer":0,"IsInZone":false,"WallId":"string","Walkable":true,"ExhibitId":"string","HangingLightId":"string"},{"Id":"ca38736b-565a-4885-9ce9-68486e022066","XPosition":-1,"YPosition":-17,"TileSetNumber":7,"TileAtlasCoOrdinateX":0,"TileAtlasCoOrdinateY":0,"Layer":0,"IsInZone":false,"WallId":"string","Walkable":true,"ExhibitId":"string","HangingLightId":"string"},{"Id":"d10f713c-5634-4f59-a945-19ddd53a16d5","XPosition":-1,"YPosition":-18,"TileSetNumber":7,"TileAtlasCoOrdinateX":0,"TileAtlasCoOrdinateY":0,"Layer":0,"IsInZone":false,"WallId":"string","Walkable":true,"ExhibitId":"string","HangingLightId":"string"},{"Id":"43bfc65d-cf17-4642-88fd-2d3a4528c216","XPosition":-1,"YPosition":-19,"TileSetNumber":7,"TileAtlasCoOrdinateX":0,"TileAtlasCoOrdinateY":0,"Layer":0,"IsInZone":false,"WallId":"basic_red_wallpaper","Walkable":true,"ExhibitId":"string","HangingLightId":"string"},{"Id":"b56b2d25-5b76-49e0-84c6-a14b567d6dac","XPosition":-2,"YPosition":0,"TileSetNumber":7,"TileAtlasCoOrdinateX":0,"TileAtlasCoOrdinateY":0,"Layer":0,"IsInZone":false,"WallId":"string","Walkable":false,"ExhibitId":"string","HangingLightId":"string"},{"Id":"da34d07a-2bd5-4c6c-bb36-23813ceb9db1","XPosition":-2,"YPosition":-1,"TileSetNumber":7,"TileAtlasCoOrdinateX":0,"TileAtlasCoOrdinateY":0,"Layer":0,"IsInZone":false,"WallId":"string","Walkable":true,"ExhibitId":"string","HangingLightId":"string"},{"Id":"d6c59fab-e613-4611-acc2-806fb166397c","XPosition":-2,"YPosition":-2,"TileSetNumber":7,"TileAtlasCoOrdinateX":0,"TileAtlasCoOrdinateY":0,"Layer":0,"IsInZone":false,"WallId":"string","Walkable":true,"ExhibitId":"string","HangingLightId":"string"},{"Id":"7e3e69e1-459f-47d0-bf1b-c8b8b3d14532","XPosition":-2,"YPosition":-3,"TileSetNumber":7,"TileAtlasCoOrdinateX":0,"TileAtlasCoOrdinateY":0,"Layer":0,"IsInZone":false,"WallId":"string","Walkable":true,"ExhibitId":"string","HangingLightId":"string"},{"Id":"3abb941f-d148-4d09-abf2-8804cadeb5ad","XPosition":-2,"YPosition":-4,"TileSetNumber":7,"TileAtlasCoOrdinateX":0,"TileAtlasCoOrdinateY":0,"Layer":0,"IsInZone":false,"WallId":"string","Walkable":true,"ExhibitId":"string","HangingLightId":"string"},{"Id":"9bb5e5a8-a500-4bfb-9a1e-74220a7e6da2","XPosition":-2,"YPosition":-5,"TileSetNumber":7,"TileAtlasCoOrdinateX":0,"TileAtlasCoOrdinateY":0,"Layer":0,"IsInZone":false,"WallId":"string","Walkable":true,"ExhibitId":"string","HangingLightId":"string"},{"Id":"680deda7-b710-4635-9ee4-f8b4a84e4272","XPosition":-2,"YPosition":-6,"TileSetNumber":7,"TileAtlasCoOrdinateX":0,"TileAtlasCoOrdinateY":0,"Layer":0,"IsInZone":false,"WallId":"string","Walkable":true,"ExhibitId":"string","HangingLightId":"string"},{"Id":"71cbc9b5-3229-41b5-b98c-63a8b1b15063","XPosition":-2,"YPosition":-7,"TileSetNumber":7,"TileAtlasCoOrdinateX":0,"TileAtlasCoOrdinateY":0,"Layer":0,"IsInZone":false,"WallId":"string","Walkable":true,"ExhibitId":"string","HangingLightId":"string"},{"Id":"d044f8e8-aa34-4576-adb8-3c3b2d2e6739","XPosition":-2,"YPosition":-8,"TileSetNumber":7,"TileAtlasCoOrdinateX":0,"TileAtlasCoOrdinateY":0,"Layer":0,"IsInZone":false,"WallId":"string","Walkable":true,"ExhibitId":"string","HangingLightId":"string"},{"Id":"fdfa2654-f20e-4f59-a165-03a5cad9cca7","XPosition":-2,"YPosition":-9,"TileSetNumber":7,"TileAtlasCoOrdinateX":0,"TileAtlasCoOrdinateY":0,"Layer":0,"IsInZone":false,"WallId":"string","Walkable":true,"ExhibitId":"string","HangingLightId":"string"},{"Id":"05be951b-6091-4ff9-aa30-49dd85759a80","XPosition":-2,"YPosition":-10,"TileSetNumber":7,"TileAtlasCoOrdinateX":0,"TileAtlasCoOrdinateY":0,"Layer":0,"IsInZone":false,"WallId":"string","Walkable":true,"ExhibitId":"string","HangingLightId":"string"},{"Id":"80dc92fe-b0f9-43c1-a162-2ed9f1377055","XPosition":-2,"YPosition":-11,"TileSetNumber":7,"TileAtlasCoOrdinateX":0,"TileAtlasCoOrdinateY":0,"Layer":0,"IsInZone":false,"WallId":"string","Walkable":true,"ExhibitId":"string","HangingLightId":"string"},{"Id":"666e21d0-7dcc-4f14-9c81-57e07cd69893","XPosition":-2,"YPosition":-12,"TileSetNumber":7,"TileAtlasCoOrdinateX":0,"TileAtlasCoOrdinateY":0,"Layer":0,"IsInZone":false,"WallId":"string","Walkable":true,"ExhibitId":"string","HangingLightId":"string"},{"Id":"4541498a-9b06-4362-a021-ee434ef14438","XPosition":-2,"YPosition":-13,"TileSetNumber":7,"TileAtlasCoOrdinateX":0,"TileAtlasCoOrdinateY":0,"Layer":0,"IsInZone":false,"WallId":"string","Walkable":true,"ExhibitId":"string","HangingLightId":"string"},{"Id":"84fabe65-8da9-4c24-b4db-438200e7e79d","XPosition":-2,"YPosition":-14,"TileSetNumber":7,"TileAtlasCoOrdinateX":0,"TileAtlasCoOrdinateY":0,"Layer":0,"IsInZone":false,"WallId":"string","Walkable":true,"ExhibitId":"string","HangingLightId":"string"},{"Id":"12743455-473b-4701-b4fe-57f5a651211e","XPosition":-2,"YPosition":-15,"TileSetNumber":7,"TileAtlasCoOrdinateX":0,"TileAtlasCoOrdinateY":0,"Layer":0,"IsInZone":false,"WallId":"string","Walkable":true,"ExhibitId":"string","HangingLightId":"string"},{"Id":"78898ae2-8b88-43eb-8932-df79641e546b","XPosition":-2,"YPosition":-16,"TileSetNumber":7,"TileAtlasCoOrdinateX":0,"TileAtlasCoOrdinateY":0,"Layer":0,"IsInZone":false,"WallId":"string","Walkable":true,"ExhibitId":"string","HangingLightId":"string"},{"Id":"b1d6eab9-1391-41ad-9301-9e5689284f22","XPosition":-2,"YPosition":-17,"TileSetNumber":7,"TileAtlasCoOrdinateX":0,"TileAtlasCoOrdinateY":0,"Layer":0,"IsInZone":false,"WallId":"string","Walkable":true,"ExhibitId":"string","HangingLightId":"string"},{"Id":"731a984f-1901-4470-90a0-3f75f6deb2f2","XPosition":-2,"YPosition":-18,"TileSetNumber":7,"TileAtlasCoOrdinateX":0,"TileAtlasCoOrdinateY":0,"Layer":0,"IsInZone":false,"WallId":"string","Walkable":true,"ExhibitId":"string","HangingLightId":"string"},{"Id":"c3b2abb8-2a01-4734-8861-24d564d8592e","XPosition":-2,"YPosition":-19,"TileSetNumber":7,"TileAtlasCoOrdinateX":0,"TileAtlasCoOrdinateY":0,"Layer":0,"IsInZone":false,"WallId":"basic_red_wallpaper","Walkable":true,"ExhibitId":"string","HangingLightId":"string"},{"Id":"169d75f6-842d-4d49-9ab5-26b84fda52ed","XPosition":-3,"YPosition":0,"TileSetNumber":7,"TileAtlasCoOrdinateX":0,"TileAtlasCoOrdinateY":0,"Layer":0,"IsInZone":false,"WallId":"string","Walkable":false,"ExhibitId":"string","HangingLightId":"string"},{"Id":"6f10f090-30c5-4ad0-8fb1-32cebfb42aba","XPosition":-3,"YPosition":-1,"TileSetNumber":7,"TileAtlasCoOrdinateX":0,"TileAtlasCoOrdinateY":0,"Layer":0,"IsInZone":false,"WallId":"string","Walkable":true,"ExhibitId":"string","HangingLightId":"string"},{"Id":"c6601437-f520-4d99-ac3e-a206a2d555a4","XPosition":-3,"YPosition":-2,"TileSetNumber":7,"TileAtlasCoOrdinateX":0,"TileAtlasCoOrdinateY":0,"Layer":0,"IsInZone":false,"WallId":"string","Walkable":true,"ExhibitId":"string","HangingLightId":"string"},{"Id":"01720a37-fb34-4ac4-8173-c00973aa15d4","XPosition":-3,"YPosition":-3,"TileSetNumber":7,"TileAtlasCoOrdinateX":0,"TileAtlasCoOrdinateY":0,"Layer":0,"IsInZone":false,"WallId":"string","Walkable":true,"ExhibitId":"string","HangingLightId":"string"},{"Id":"09b0ac3e-8131-4c45-a52f-2df752e04bdd","XPosition":-3,"YPosition":-4,"TileSetNumber":7,"TileAtlasCoOrdinateX":0,"TileAtlasCoOrdinateY":0,"Layer":0,"IsInZone":false,"WallId":"string","Walkable":true,"ExhibitId":"string","HangingLightId":"string"},{"Id":"ca138453-41a4-47f2-ab3e-3f450de74f7b","XPosition":-3,"YPosition":-5,"TileSetNumber":7,"TileAtlasCoOrdinateX":0,"TileAtlasCoOrdinateY":0,"Layer":0,"IsInZone":false,"WallId":"string","Walkable":true,"ExhibitId":"string","HangingLightId":"string"},{"Id":"075b41bd-e549-4ea9-bb27-5725e7219fb0","XPosition":-3,"YPosition":-6,"TileSetNumber":7,"TileAtlasCoOrdinateX":0,"TileAtlasCoOrdinateY":0,"Layer":0,"IsInZone":false,"WallId":"string","Walkable":true,"ExhibitId":"string","HangingLightId":"string"},{"Id":"eee10603-88fa-4adf-bec1-5e11cf903956","XPosition":-3,"YPosition":-7,"TileSetNumber":7,"TileAtlasCoOrdinateX":0,"TileAtlasCoOrdinateY":0,"Layer":0,"IsInZone":false,"WallId":"string","Walkable":true,"ExhibitId":"string","HangingLightId":"string"},{"Id":"385db8d3-33a8-4f98-86cb-8ce62b87686f","XPosition":-3,"YPosition":-8,"TileSetNumber":7,"TileAtlasCoOrdinateX":0,"TileAtlasCoOrdinateY":0,"Layer":0,"IsInZone":false,"WallId":"string","Walkable":true,"ExhibitId":"string","HangingLightId":"string"},{"Id":"b43ef908-c733-407a-a85f-40d69bb05cc4","XPosition":-3,"YPosition":-9,"TileSetNumber":7,"TileAtlasCoOrdinateX":0,"TileAtlasCoOrdinateY":0,"Layer":0,"IsInZone":false,"WallId":"string","Walkable":true,"ExhibitId":"string","HangingLightId":"string"},{"Id":"e5ea010d-a529-4b40-95ac-a88fb7efb611","XPosition":-3,"YPosition":-10,"TileSetNumber":7,"TileAtlasCoOrdinateX":0,"TileAtlasCoOrdinateY":0,"Layer":0,"IsInZone":false,"WallId":"string","Walkable":true,"ExhibitId":"string","HangingLightId":"string"},{"Id":"930ee57c-548d-4c32-b3f2-5a37768e80a5","XPosition":-3,"YPosition":-11,"TileSetNumber":7,"TileAtlasCoOrdinateX":0,"TileAtlasCoOrdinateY":0,"Layer":0,"IsInZone":false,"WallId":"string","Walkable":true,"ExhibitId":"string","HangingLightId":"string"},{"Id":"1fac6caf-129f-4df0-a75c-99d30fc1fb75","XPosition":-3,"YPosition":-12,"TileSetNumber":7,"TileAtlasCoOrdinateX":0,"TileAtlasCoOrdinateY":0,"Layer":0,"IsInZone":false,"WallId":"string","Walkable":true,"ExhibitId":"string","HangingLightId":"string"},{"Id":"f3c255fe-05ae-43ad-b287-3445b4a1946d","XPosition":-3,"YPosition":-13,"TileSetNumber":7,"TileAtlasCoOrdinateX":0,"TileAtlasCoOrdinateY":0,"Layer":0,"IsInZone":false,"WallId":"string","Walkable":true,"ExhibitId":"string","HangingLightId":"string"},{"Id":"b118112e-fe7d-45ca-96b5-0f2025ad37cb","XPosition":-3,"YPosition":-14,"TileSetNumber":7,"TileAtlasCoOrdinateX":0,"TileAtlasCoOrdinateY":0,"Layer":0,"IsInZone":false,"WallId":"string","Walkable":true,"ExhibitId":"string","HangingLightId":"string"},{"Id":"c8cbb540-a388-4c80-84b5-458785488f56","XPosition":-3,"YPosition":-15,"TileSetNumber":7,"TileAtlasCoOrdinateX":0,"TileAtlasCoOrdinateY":0,"Layer":0,"IsInZone":false,"WallId":"string","Walkable":true,"ExhibitId":"string","HangingLightId":"string"},{"Id":"7bf0b988-b269-4f09-b18f-7a84611534a8","XPosition":-3,"YPosition":-16,"TileSetNumber":7,"TileAtlasCoOrdinateX":0,"TileAtlasCoOrdinateY":0,"Layer":0,"IsInZone":false,"WallId":"string","Walkable":true,"ExhibitId":"string","HangingLightId":"string"},{"Id":"e6a485c7-f14d-4980-bebc-46f1e6850f2f","XPosition":-3,"YPosition":-17,"TileSetNumber":7,"TileAtlasCoOrdinateX":0,"TileAtlasCoOrdinateY":0,"Layer":0,"IsInZone":false,"WallId":"string","Walkable":true,"ExhibitId":"string","HangingLightId":"string"},{"Id":"e48e4644-b4fe-44eb-8bc8-f58d7baf21fc","XPosition":-3,"YPosition":-18,"TileSetNumber":7,"TileAtlasCoOrdinateX":0,"TileAtlasCoOrdinateY":0,"Layer":0,"IsInZone":false,"WallId":"string","Walkable":true,"ExhibitId":"string","HangingLightId":"string"},{"Id":"b2d571f1-5ea9-4b16-9c28-64bba3f78c4d","XPosition":-3,"YPosition":-19,"TileSetNumber":7,"TileAtlasCoOrdinateX":0,"TileAtlasCoOrdinateY":0,"Layer":0,"IsInZone":false,"WallId":"basic_red_wallpaper","Walkable":true,"ExhibitId":"string","HangingLightId":"string"},{"Id":"7dbe6933-5e02-4d4f-939b-864e05beed42","XPosition":-4,"YPosition":0,"TileSetNumber":7,"TileAtlasCoOrdinateX":0,"TileAtlasCoOrdinateY":0,"Layer":0,"IsInZone":false,"WallId":"string","Walkable":false,"ExhibitId":"string","HangingLightId":"string"},{"Id":"8c02d823-0837-4a2a-b9f6-5609bf034aaf","XPosition":-4,"YPosition":-1,"TileSetNumber":7,"TileAtlasCoOrdinateX":0,"TileAtlasCoOrdinateY":0,"Layer":0,"IsInZone":false,"WallId":"string","Walkable":true,"ExhibitId":"string","HangingLightId":"string"},{"Id":"7ae3f9d4-6cee-461b-917f-89578d037931","XPosition":-4,"YPosition":-2,"TileSetNumber":7,"TileAtlasCoOrdinateX":0,"TileAtlasCoOrdinateY":0,"Layer":0,"IsInZone":false,"WallId":"string","Walkable":true,"ExhibitId":"string","HangingLightId":"string"},{"Id":"ad06445b-ce18-44ff-b7e5-c1e88d98da22","XPosition":-4,"YPosition":-3,"TileSetNumber":7,"TileAtlasCoOrdinateX":0,"TileAtlasCoOrdinateY":0,"Layer":0,"IsInZone":false,"WallId":"string","Walkable":true,"ExhibitId":"string","HangingLightId":"string"},{"Id":"dad6dc27-4392-4013-bd5d-6c1fc7424756","XPosition":-4,"YPosition":-4,"TileSetNumber":7,"TileAtlasCoOrdinateX":0,"TileAtlasCoOrdinateY":0,"Layer":0,"IsInZone":false,"WallId":"string","Walkable":true,"ExhibitId":"string","HangingLightId":"string"},{"Id":"37768cd0-e22f-484d-b432-c950e42eb474","XPosition":-4,"YPosition":-5,"TileSetNumber":7,"TileAtlasCoOrdinateX":0,"TileAtlasCoOrdinateY":0,"Layer":0,"IsInZone":false,"WallId":"string","Walkable":true,"ExhibitId":"string","HangingLightId":"string"},{"Id":"7b5680c9-fbd7-4a1a-9cd8-96c42866b0f9","XPosition":-4,"YPosition":-6,"TileSetNumber":7,"TileAtlasCoOrdinateX":0,"TileAtlasCoOrdinateY":0,"Layer":0,"IsInZone":false,"WallId":"string","Walkable":true,"ExhibitId":"string","HangingLightId":"string"},{"Id":"89c61cc0-fc3f-46e2-accf-86dc5e8acb64","XPosition":-4,"YPosition":-7,"TileSetNumber":7,"TileAtlasCoOrdinateX":0,"TileAtlasCoOrdinateY":0,"Layer":0,"IsInZone":false,"WallId":"string","Walkable":true,"ExhibitId":"string","HangingLightId":"string"},{"Id":"0bef47d2-a1e1-471a-8678-977f1a823863","XPosition":-4,"YPosition":-8,"TileSetNumber":7,"TileAtlasCoOrdinateX":0,"TileAtlasCoOrdinateY":0,"Layer":0,"IsInZone":false,"WallId":"string","Walkable":true,"ExhibitId":"string","HangingLightId":"string"},{"Id":"498336a8-7b38-46ed-9c12-63d298bcb5a3","XPosition":-4,"YPosition":-9,"TileSetNumber":7,"TileAtlasCoOrdinateX":0,"TileAtlasCoOrdinateY":0,"Layer":0,"IsInZone":false,"WallId":"string","Walkable":true,"ExhibitId":"string","HangingLightId":"string"},{"Id":"8f87d740-e512-499f-9b91-c9d96c5b9bdb","XPosition":-4,"YPosition":-10,"TileSetNumber":7,"TileAtlasCoOrdinateX":0,"TileAtlasCoOrdinateY":0,"Layer":0,"IsInZone":false,"WallId":"string","Walkable":true,"ExhibitId":"string","HangingLightId":"string"},{"Id":"7df13816-071f-4a3b-af4b-5debfc7b1537","XPosition":-4,"YPosition":-11,"TileSetNumber":7,"TileAtlasCoOrdinateX":0,"TileAtlasCoOrdinateY":0,"Layer":0,"IsInZone":false,"WallId":"string","Walkable":true,"ExhibitId":"string","HangingLightId":"string"},{"Id":"0855cdab-c1ef-4ee6-996c-802448ae1508","XPosition":-4,"YPosition":-12,"TileSetNumber":7,"TileAtlasCoOrdinateX":0,"TileAtlasCoOrdinateY":0,"Layer":0,"IsInZone":false,"WallId":"string","Walkable":true,"ExhibitId":"string","HangingLightId":"string"},{"Id":"63042cf7-5853-48c3-bb95-056db7eb7b5d","XPosition":-4,"YPosition":-13,"TileSetNumber":7,"TileAtlasCoOrdinateX":0,"TileAtlasCoOrdinateY":0,"Layer":0,"IsInZone":false,"WallId":"string","Walkable":true,"ExhibitId":"string","HangingLightId":"string"},{"Id":"83741b46-0e3d-4bea-a8cd-a9b707d222d4","XPosition":-4,"YPosition":-14,"TileSetNumber":7,"TileAtlasCoOrdinateX":0,"TileAtlasCoOrdinateY":0,"Layer":0,"IsInZone":false,"WallId":"string","Walkable":true,"ExhibitId":"string","HangingLightId":"string"},{"Id":"8269a5dd-40f9-4017-8abf-c21750f418d9","XPosition":-4,"YPosition":-15,"TileSetNumber":7,"TileAtlasCoOrdinateX":0,"TileAtlasCoOrdinateY":0,"Layer":0,"IsInZone":false,"WallId":"string","Walkable":true,"ExhibitId":"string","HangingLightId":"string"},{"Id":"887fc7dc-9f99-4a38-9d6c-2067f6664cde","XPosition":-4,"YPosition":-16,"TileSetNumber":7,"TileAtlasCoOrdinateX":0,"TileAtlasCoOrdinateY":0,"Layer":0,"IsInZone":false,"WallId":"string","Walkable":true,"ExhibitId":"string","HangingLightId":"string"},{"Id":"ef8e2c72-894e-4ee0-a7aa-9850b056ed89","XPosition":-4,"YPosition":-17,"TileSetNumber":7,"TileAtlasCoOrdinateX":0,"TileAtlasCoOrdinateY":0,"Layer":0,"IsInZone":false,"WallId":"string","Walkable":true,"ExhibitId":"string","HangingLightId":"string"},{"Id":"53fa0c67-a8a5-4040-8b68-a273547d7ff2","XPosition":-4,"YPosition":-18,"TileSetNumber":7,"TileAtlasCoOrdinateX":0,"TileAtlasCoOrdinateY":0,"Layer":0,"IsInZone":false,"WallId":"string","Walkable":true,"ExhibitId":"string","HangingLightId":"string"},{"Id":"b3777a65-a14c-457a-b313-60c1aa5f2ad7","XPosition":-4,"YPosition":-19,"TileSetNumber":7,"TileAtlasCoOrdinateX":0,"TileAtlasCoOrdinateY":0,"Layer":0,"IsInZone":false,"WallId":"basic_red_wallpaper","Walkable":true,"ExhibitId":"string","HangingLightId":"string"},{"Id":"76688d24-58f0-4386-8277-1a29959c6020","XPosition":-5,"YPosition":0,"TileSetNumber":7,"TileAtlasCoOrdinateX":0,"TileAtlasCoOrdinateY":0,"Layer":0,"IsInZone":false,"WallId":"string","Walkable":false,"ExhibitId":"string","HangingLightId":"string"},{"Id":"d55a19c9-7b02-4ff7-bd23-91eb1bb3c8c3","XPosition":-5,"YPosition":-1,"TileSetNumber":7,"TileAtlasCoOrdinateX":0,"TileAtlasCoOrdinateY":0,"Layer":0,"IsInZone":false,"WallId":"string","Walkable":true,"ExhibitId":"string","HangingLightId":"string"},{"Id":"a611ffe4-7977-46e3-9bea-6f5320e877da","XPosition":-5,"YPosition":-2,"TileSetNumber":7,"TileAtlasCoOrdinateX":0,"TileAtlasCoOrdinateY":0,"Layer":0,"IsInZone":false,"WallId":"string","Walkable":true,"ExhibitId":"string","HangingLightId":"string"},{"Id":"fb65afff-ec4c-4e4d-b7e1-1d23d7db3c47","XPosition":-5,"YPosition":-3,"TileSetNumber":7,"TileAtlasCoOrdinateX":0,"TileAtlasCoOrdinateY":0,"Layer":0,"IsInZone":false,"WallId":"string","Walkable":true,"ExhibitId":"string","HangingLightId":"string"},{"Id":"29d901ea-1080-4776-9743-73030cec2c41","XPosition":-5,"YPosition":-4,"TileSetNumber":7,"TileAtlasCoOrdinateX":0,"TileAtlasCoOrdinateY":0,"Layer":0,"IsInZone":false,"WallId":"string","Walkable":true,"ExhibitId":"string","HangingLightId":"string"},{"Id":"65f73a53-fba9-4970-8cea-cb31b8c24153","XPosition":-5,"YPosition":-5,"TileSetNumber":7,"TileAtlasCoOrdinateX":0,"TileAtlasCoOrdinateY":0,"Layer":0,"IsInZone":false,"WallId":"string","Walkable":true,"ExhibitId":"string","HangingLightId":"string"},{"Id":"a33ce137-7897-40d0-b2a7-407fd3e5fd80","XPosition":-5,"YPosition":-6,"TileSetNumber":7,"TileAtlasCoOrdinateX":0,"TileAtlasCoOrdinateY":0,"Layer":0,"IsInZone":false,"WallId":"string","Walkable":true,"ExhibitId":"string","HangingLightId":"string"},{"Id":"9f8933a8-e5bb-49c3-a62d-2d1f3bb23149","XPosition":-5,"YPosition":-7,"TileSetNumber":7,"TileAtlasCoOrdinateX":0,"TileAtlasCoOrdinateY":0,"Layer":0,"IsInZone":false,"WallId":"string","Walkable":true,"ExhibitId":"string","HangingLightId":"string"},{"Id":"aca4242e-773d-4bfc-9982-2fee6b5f57a8","XPosition":-5,"YPosition":-8,"TileSetNumber":7,"TileAtlasCoOrdinateX":0,"TileAtlasCoOrdinateY":0,"Layer":0,"IsInZone":false,"WallId":"string","Walkable":true,"ExhibitId":"string","HangingLightId":"string"},{"Id":"1c59df71-6213-4096-ad1d-90c64cce5119","XPosition":-5,"YPosition":-9,"TileSetNumber":7,"TileAtlasCoOrdinateX":0,"TileAtlasCoOrdinateY":0,"Layer":0,"IsInZone":false,"WallId":"string","Walkable":true,"ExhibitId":"string","HangingLightId":"string"},{"Id":"9c61ed30-2608-4823-87a6-068e4859b2ae","XPosition":-5,"YPosition":-10,"TileSetNumber":7,"TileAtlasCoOrdinateX":0,"TileAtlasCoOrdinateY":0,"Layer":0,"IsInZone":false,"WallId":"string","Walkable":true,"ExhibitId":"string","HangingLightId":"string"},{"Id":"8e58088e-409d-49ee-a7b5-5b8acd5fd413","XPosition":-5,"YPosition":-11,"TileSetNumber":7,"TileAtlasCoOrdinateX":0,"TileAtlasCoOrdinateY":0,"Layer":0,"IsInZone":false,"WallId":"string","Walkable":true,"ExhibitId":"string","HangingLightId":"string"},{"Id":"24f82284-eb89-4162-b0be-b122bfac1beb","XPosition":-5,"YPosition":-12,"TileSetNumber":7,"TileAtlasCoOrdinateX":0,"TileAtlasCoOrdinateY":0,"Layer":0,"IsInZone":false,"WallId":"string","Walkable":true,"ExhibitId":"string","HangingLightId":"string"},{"Id":"57e43a52-a624-4325-acf6-cdb6230ab50a","XPosition":-5,"YPosition":-13,"TileSetNumber":7,"TileAtlasCoOrdinateX":0,"TileAtlasCoOrdinateY":0,"Layer":0,"IsInZone":false,"WallId":"string","Walkable":true,"ExhibitId":"string","HangingLightId":"string"},{"Id":"695cb24e-8441-4c56-b4ed-4c113abd6dc3","XPosition":-5,"YPosition":-14,"TileSetNumber":7,"TileAtlasCoOrdinateX":0,"TileAtlasCoOrdinateY":0,"Layer":0,"IsInZone":false,"WallId":"string","Walkable":true,"ExhibitId":"string","HangingLightId":"string"},{"Id":"ab2aba56-dc13-4a1b-8d1c-f35fbc4d819f","XPosition":-5,"YPosition":-15,"TileSetNumber":7,"TileAtlasCoOrdinateX":0,"TileAtlasCoOrdinateY":0,"Layer":0,"IsInZone":false,"WallId":"string","Walkable":true,"ExhibitId":"string","HangingLightId":"string"},{"Id":"d5faf003-cab4-42a0-892e-8b52eba3895b","XPosition":-5,"YPosition":-16,"TileSetNumber":7,"TileAtlasCoOrdinateX":0,"TileAtlasCoOrdinateY":0,"Layer":0,"IsInZone":false,"WallId":"string","Walkable":true,"ExhibitId":"string","HangingLightId":"string"},{"Id":"b217df86-16cf-46f5-b3ee-17d625317ac8","XPosition":-5,"YPosition":-17,"TileSetNumber":7,"TileAtlasCoOrdinateX":0,"TileAtlasCoOrdinateY":0,"Layer":0,"IsInZone":false,"WallId":"string","Walkable":true,"ExhibitId":"string","HangingLightId":"string"},{"Id":"32255637-5923-4271-9c78-9deb387f65cf","XPosition":-5,"YPosition":-18,"TileSetNumber":7,"TileAtlasCoOrdinateX":0,"TileAtlasCoOrdinateY":0,"Layer":0,"IsInZone":false,"WallId":"string","Walkable":true,"ExhibitId":"string","HangingLightId":"string"},{"Id":"daf85703-2423-4649-87dd-71115f33a6c0","XPosition":-5,"YPosition":-19,"TileSetNumber":7,"TileAtlasCoOrdinateX":0,"TileAtlasCoOrdinateY":0,"Layer":0,"IsInZone":false,"WallId":"basic_red_wallpaper","Walkable":true,"ExhibitId":"string","HangingLightId":"string"},{"Id":"b67b6140-7d78-47b0-89c2-d6170eb175a9","XPosition":-6,"YPosition":0,"TileSetNumber":7,"TileAtlasCoOrdinateX":0,"TileAtlasCoOrdinateY":0,"Layer":0,"IsInZone":false,"WallId":"string","Walkable":false,"ExhibitId":"string","HangingLightId":"string"},{"Id":"f7fa40a6-6110-4dd5-aa7f-ecfcda32eeb3","XPosition":-6,"YPosition":-1,"TileSetNumber":7,"TileAtlasCoOrdinateX":0,"TileAtlasCoOrdinateY":0,"Layer":0,"IsInZone":false,"WallId":"string","Walkable":true,"ExhibitId":"string","HangingLightId":"string"},{"Id":"8f832b20-b649-49ca-8a0a-7deeb37f58db","XPosition":-6,"YPosition":-2,"TileSetNumber":7,"TileAtlasCoOrdinateX":0,"TileAtlasCoOrdinateY":0,"Layer":0,"IsInZone":false,"WallId":"string","Walkable":true,"ExhibitId":"string","HangingLightId":"string"},{"Id":"5354e80e-8b66-4383-afb5-108391255002","XPosition":-6,"YPosition":-3,"TileSetNumber":7,"TileAtlasCoOrdinateX":0,"TileAtlasCoOrdinateY":0,"Layer":0,"IsInZone":false,"WallId":"string","Walkable":true,"ExhibitId":"string","HangingLightId":"string"},{"Id":"5f7d4263-c834-4970-9d11-e6404c97c92a","XPosition":-6,"YPosition":-4,"TileSetNumber":7,"TileAtlasCoOrdinateX":0,"TileAtlasCoOrdinateY":0,"Layer":0,"IsInZone":false,"WallId":"string","Walkable":true,"ExhibitId":"string","HangingLightId":"string"},{"Id":"5b33ae01-40a6-49a7-abbd-f30aa3e75187","XPosition":-6,"YPosition":-5,"TileSetNumber":7,"TileAtlasCoOrdinateX":0,"TileAtlasCoOrdinateY":0,"Layer":0,"IsInZone":false,"WallId":"string","Walkable":true,"ExhibitId":"string","HangingLightId":"string"},{"Id":"426e561a-e810-4f21-b7b5-9c18ec068531","XPosition":-6,"YPosition":-6,"TileSetNumber":7,"TileAtlasCoOrdinateX":0,"TileAtlasCoOrdinateY":0,"Layer":0,"IsInZone":false,"WallId":"string","Walkable":true,"ExhibitId":"string","HangingLightId":"string"},{"Id":"25a191e4-6654-498a-85b8-ecd4066d4449","XPosition":-6,"YPosition":-7,"TileSetNumber":7,"TileAtlasCoOrdinateX":0,"TileAtlasCoOrdinateY":0,"Layer":0,"IsInZone":false,"WallId":"string","Walkable":true,"ExhibitId":"string","HangingLightId":"string"},{"Id":"ce3e635a-4de5-4768-a302-233157376ebc","XPosition":-6,"YPosition":-8,"TileSetNumber":7,"TileAtlasCoOrdinateX":0,"TileAtlasCoOrdinateY":0,"Layer":0,"IsInZone":false,"WallId":"string","Walkable":true,"ExhibitId":"string","HangingLightId":"string"},{"Id":"3b514098-86d3-4c02-821d-8e5738354b80","XPosition":-6,"YPosition":-9,"TileSetNumber":7,"TileAtlasCoOrdinateX":0,"TileAtlasCoOrdinateY":0,"Layer":0,"IsInZone":false,"WallId":"string","Walkable":true,"ExhibitId":"string","HangingLightId":"string"},{"Id":"24557037-63b3-4fb8-b04a-1195dbdd5456","XPosition":-6,"YPosition":-10,"TileSetNumber":7,"TileAtlasCoOrdinateX":0,"TileAtlasCoOrdinateY":0,"Layer":0,"IsInZone":false,"WallId":"string","Walkable":true,"ExhibitId":"string","HangingLightId":"string"},{"Id":"a9b554f2-35d6-45fc-bfeb-f7ee116a8c48","XPosition":-6,"YPosition":-11,"TileSetNumber":7,"TileAtlasCoOrdinateX":0,"TileAtlasCoOrdinateY":0,"Layer":0,"IsInZone":false,"WallId":"string","Walkable":true,"ExhibitId":"string","HangingLightId":"string"},{"Id":"941e2bb2-eeb7-4e21-bbf0-f8d1cd390510","XPosition":-6,"YPosition":-12,"TileSetNumber":7,"TileAtlasCoOrdinateX":0,"TileAtlasCoOrdinateY":0,"Layer":0,"IsInZone":false,"WallId":"string","Walkable":true,"ExhibitId":"string","HangingLightId":"string"},{"Id":"17cd1473-95c2-4d70-8df2-c0cc98034efe","XPosition":-6,"YPosition":-13,"TileSetNumber":7,"TileAtlasCoOrdinateX":0,"TileAtlasCoOrdinateY":0,"Layer":0,"IsInZone":false,"WallId":"string","Walkable":true,"ExhibitId":"string","HangingLightId":"string"},{"Id":"4a8be5f6-241c-4813-ac89-b06a8a374d50","XPosition":-6,"YPosition":-14,"TileSetNumber":7,"TileAtlasCoOrdinateX":0,"TileAtlasCoOrdinateY":0,"Layer":0,"IsInZone":false,"WallId":"string","Walkable":true,"ExhibitId":"string","HangingLightId":"string"},{"Id":"0c69c8db-4709-4d65-b623-ffedc322b11d","XPosition":-6,"YPosition":-15,"TileSetNumber":7,"TileAtlasCoOrdinateX":0,"TileAtlasCoOrdinateY":0,"Layer":0,"IsInZone":false,"WallId":"string","Walkable":true,"ExhibitId":"string","HangingLightId":"string"},{"Id":"8e32b011-3aa3-4ee7-bc6f-8043effb800c","XPosition":-6,"YPosition":-16,"TileSetNumber":7,"TileAtlasCoOrdinateX":0,"TileAtlasCoOrdinateY":0,"Layer":0,"IsInZone":false,"WallId":"string","Walkable":true,"ExhibitId":"string","HangingLightId":"string"},{"Id":"bd30b3df-b02e-41ac-a970-8230e85c74b1","XPosition":-6,"YPosition":-17,"TileSetNumber":7,"TileAtlasCoOrdinateX":0,"TileAtlasCoOrdinateY":0,"Layer":0,"IsInZone":false,"WallId":"string","Walkable":true,"ExhibitId":"string","HangingLightId":"string"},{"Id":"47fa13ca-e310-4891-81c6-445974b5fc3d","XPosition":-6,"YPosition":-18,"TileSetNumber":7,"TileAtlasCoOrdinateX":0,"TileAtlasCoOrdinateY":0,"Layer":0,"IsInZone":false,"WallId":"string","Walkable":true,"ExhibitId":"string","HangingLightId":"string"},{"Id":"e96e255a-881e-430b-b0fb-270cf97c188c","XPosition":-6,"YPosition":-19,"TileSetNumber":7,"TileAtlasCoOrdinateX":0,"TileAtlasCoOrdinateY":0,"Layer":0,"IsInZone":false,"WallId":"basic_red_wallpaper","Walkable":true,"ExhibitId":"string","HangingLightId":"string"},{"Id":"d920ecc1-aa36-4752-98f8-f48d0647696d","XPosition":-7,"YPosition":0,"TileSetNumber":7,"TileAtlasCoOrdinateX":0,"TileAtlasCoOrdinateY":0,"Layer":0,"IsInZone":false,"WallId":"string","Walkable":false,"ExhibitId":"string","HangingLightId":"string"},{"Id":"ece4fb83-50ff-4b9e-8c93-b27842b8a7dc","XPosition":-7,"YPosition":-1,"TileSetNumber":7,"TileAtlasCoOrdinateX":0,"TileAtlasCoOrdinateY":0,"Layer":0,"IsInZone":false,"WallId":"string","Walkable":true,"ExhibitId":"string","HangingLightId":"string"},{"Id":"879320e5-c246-49ea-a4f9-b37efaa4cb56","XPosition":-7,"YPosition":-2,"TileSetNumber":7,"TileAtlasCoOrdinateX":0,"TileAtlasCoOrdinateY":0,"Layer":0,"IsInZone":false,"WallId":"string","Walkable":true,"ExhibitId":"string","HangingLightId":"string"},{"Id":"e7cdc25e-29c2-423c-82e6-162b7156be0e","XPosition":-7,"YPosition":-3,"TileSetNumber":7,"TileAtlasCoOrdinateX":0,"TileAtlasCoOrdinateY":0,"Layer":0,"IsInZone":false,"WallId":"string","Walkable":true,"ExhibitId":"string","HangingLightId":"string"},{"Id":"3e303ee3-710d-4dce-adf5-ba04b7597014","XPosition":-7,"YPosition":-4,"TileSetNumber":7,"TileAtlasCoOrdinateX":0,"TileAtlasCoOrdinateY":0,"Layer":0,"IsInZone":false,"WallId":"string","Walkable":true,"ExhibitId":"string","HangingLightId":"string"},{"Id":"9268155e-0ca5-4c2c-a9b8-48cb402b5b4a","XPosition":-7,"YPosition":-5,"TileSetNumber":7,"TileAtlasCoOrdinateX":0,"TileAtlasCoOrdinateY":0,"Layer":0,"IsInZone":false,"WallId":"string","Walkable":true,"ExhibitId":"string","HangingLightId":"string"},{"Id":"2cb20f4f-28fe-4355-affb-76a416d7267e","XPosition":-7,"YPosition":-6,"TileSetNumber":7,"TileAtlasCoOrdinateX":0,"TileAtlasCoOrdinateY":0,"Layer":0,"IsInZone":false,"WallId":"string","Walkable":true,"ExhibitId":"string","HangingLightId":"string"},{"Id":"049356dc-f010-42d4-8190-244e6dd1fc62","XPosition":-7,"YPosition":-7,"TileSetNumber":7,"TileAtlasCoOrdinateX":0,"TileAtlasCoOrdinateY":0,"Layer":0,"IsInZone":false,"WallId":"string","Walkable":true,"ExhibitId":"string","HangingLightId":"string"},{"Id":"143003a9-9e55-4ef7-8013-6468fa3133e3","XPosition":-7,"YPosition":-8,"TileSetNumber":7,"TileAtlasCoOrdinateX":0,"TileAtlasCoOrdinateY":0,"Layer":0,"IsInZone":false,"WallId":"string","Walkable":true,"ExhibitId":"string","HangingLightId":"string"},{"Id":"f7d9689b-f7c8-420c-b001-a659513ebfb2","XPosition":-7,"YPosition":-9,"TileSetNumber":7,"TileAtlasCoOrdinateX":0,"TileAtlasCoOrdinateY":0,"Layer":0,"IsInZone":false,"WallId":"string","Walkable":true,"ExhibitId":"string","HangingLightId":"string"},{"Id":"c68669a8-96ad-4131-b379-136a14c794c9","XPosition":-7,"YPosition":-10,"TileSetNumber":7,"TileAtlasCoOrdinateX":0,"TileAtlasCoOrdinateY":0,"Layer":0,"IsInZone":false,"WallId":"string","Walkable":true,"ExhibitId":"string","HangingLightId":"string"},{"Id":"5d2411c6-5f3a-4221-ab96-9a2cfc177ccd","XPosition":-7,"YPosition":-11,"TileSetNumber":7,"TileAtlasCoOrdinateX":0,"TileAtlasCoOrdinateY":0,"Layer":0,"IsInZone":false,"WallId":"string","Walkable":true,"ExhibitId":"string","HangingLightId":"string"},{"Id":"e4ce31ea-5bf0-4658-87e3-fcf23a812960","XPosition":-7,"YPosition":-12,"TileSetNumber":7,"TileAtlasCoOrdinateX":0,"TileAtlasCoOrdinateY":0,"Layer":0,"IsInZone":false,"WallId":"string","Walkable":true,"ExhibitId":"string","HangingLightId":"string"},{"Id":"8bb8b621-7724-4298-8669-c708f654a021","XPosition":-7,"YPosition":-13,"TileSetNumber":7,"TileAtlasCoOrdinateX":0,"TileAtlasCoOrdinateY":0,"Layer":0,"IsInZone":false,"WallId":"string","Walkable":true,"ExhibitId":"string","HangingLightId":"string"},{"Id":"762d77eb-139e-4d04-aa5a-dd69f9b1d2f1","XPosition":-7,"YPosition":-14,"TileSetNumber":7,"TileAtlasCoOrdinateX":0,"TileAtlasCoOrdinateY":0,"Layer":0,"IsInZone":false,"WallId":"string","Walkable":true,"ExhibitId":"string","HangingLightId":"string"},{"Id":"6737e8c0-0541-40c4-863b-f37c0774f17b","XPosition":-7,"YPosition":-15,"TileSetNumber":7,"TileAtlasCoOrdinateX":0,"TileAtlasCoOrdinateY":0,"Layer":0,"IsInZone":false,"WallId":"string","Walkable":true,"ExhibitId":"string","HangingLightId":"string"},{"Id":"6969d5b6-ddae-40f8-b68b-8ddf3631bc61","XPosition":-7,"YPosition":-16,"TileSetNumber":7,"TileAtlasCoOrdinateX":0,"TileAtlasCoOrdinateY":0,"Layer":0,"IsInZone":false,"WallId":"string","Walkable":true,"ExhibitId":"string","HangingLightId":"string"},{"Id":"eba0633d-861b-471e-9c66-82a500dc75dc","XPosition":-7,"YPosition":-17,"TileSetNumber":7,"TileAtlasCoOrdinateX":0,"TileAtlasCoOrdinateY":0,"Layer":0,"IsInZone":false,"WallId":"string","Walkable":true,"ExhibitId":"string","HangingLightId":"string"},{"Id":"1199085b-35f2-498f-b761-54cc45e0e395","XPosition":-7,"YPosition":-18,"TileSetNumber":7,"TileAtlasCoOrdinateX":0,"TileAtlasCoOrdinateY":0,"Layer":0,"IsInZone":false,"WallId":"string","Walkable":true,"ExhibitId":"string","HangingLightId":"string"},{"Id":"7b2ab02c-797c-4b67-b6e5-1cc70eb48d25","XPosition":-7,"YPosition":-19,"TileSetNumber":7,"TileAtlasCoOrdinateX":0,"TileAtlasCoOrdinateY":0,"Layer":0,"IsInZone":false,"WallId":"basic_red_wallpaper","Walkable":true,"ExhibitId":"string","HangingLightId":"string"},{"Id":"2cfd331f-f662-4ce7-b1b6-ef2ea3f31250","XPosition":-8,"YPosition":0,"TileSetNumber":7,"TileAtlasCoOrdinateX":0,"TileAtlasCoOrdinateY":0,"Layer":0,"IsInZone":false,"WallId":"string","Walkable":false,"ExhibitId":"string","HangingLightId":"string"},{"Id":"6e345e01-80ea-46a4-931d-5be133f6f77a","XPosition":-8,"YPosition":-1,"TileSetNumber":7,"TileAtlasCoOrdinateX":0,"TileAtlasCoOrdinateY":0,"Layer":0,"IsInZone":false,"WallId":"string","Walkable":true,"ExhibitId":"string","HangingLightId":"string"},{"Id":"c9e4eb44-cd1c-402c-bd43-542d29a95348","XPosition":-8,"YPosition":-2,"TileSetNumber":7,"TileAtlasCoOrdinateX":0,"TileAtlasCoOrdinateY":0,"Layer":0,"IsInZone":false,"WallId":"string","Walkable":true,"ExhibitId":"string","HangingLightId":"string"},{"Id":"57f0b768-0c66-4df9-bbbc-7f8198b916e5","XPosition":-8,"YPosition":-3,"TileSetNumber":7,"TileAtlasCoOrdinateX":0,"TileAtlasCoOrdinateY":0,"Layer":0,"IsInZone":false,"WallId":"string","Walkable":true,"ExhibitId":"string","HangingLightId":"string"},{"Id":"e882c398-b610-4bcc-ac48-b77c75d7a99d","XPosition":-8,"YPosition":-4,"TileSetNumber":7,"TileAtlasCoOrdinateX":0,"TileAtlasCoOrdinateY":0,"Layer":0,"IsInZone":false,"WallId":"string","Walkable":true,"ExhibitId":"string","HangingLightId":"string"},{"Id":"c0c03414-e3e1-405d-b00a-156fdd8048ff","XPosition":-8,"YPosition":-5,"TileSetNumber":7,"TileAtlasCoOrdinateX":0,"TileAtlasCoOrdinateY":0,"Layer":0,"IsInZone":false,"WallId":"string","Walkable":true,"ExhibitId":"string","HangingLightId":"string"},{"Id":"ba236d84-2703-473a-9739-bae66e16bb07","XPosition":-8,"YPosition":-6,"TileSetNumber":7,"TileAtlasCoOrdinateX":0,"TileAtlasCoOrdinateY":0,"Layer":0,"IsInZone":false,"WallId":"string","Walkable":true,"ExhibitId":"string","HangingLightId":"string"},{"Id":"b370f31b-0147-44bf-9787-59b2c71f76fb","XPosition":-8,"YPosition":-7,"TileSetNumber":7,"TileAtlasCoOrdinateX":0,"TileAtlasCoOrdinateY":0,"Layer":0,"IsInZone":false,"WallId":"string","Walkable":true,"ExhibitId":"string","HangingLightId":"string"},{"Id":"62247082-d686-47be-ad94-3e98fe0c7376","XPosition":-8,"YPosition":-8,"TileSetNumber":7,"TileAtlasCoOrdinateX":0,"TileAtlasCoOrdinateY":0,"Layer":0,"IsInZone":false,"WallId":"string","Walkable":true,"ExhibitId":"string","HangingLightId":"string"},{"Id":"d5780877-39df-4efa-8c07-23d56898154c","XPosition":-8,"YPosition":-9,"TileSetNumber":7,"TileAtlasCoOrdinateX":0,"TileAtlasCoOrdinateY":0,"Layer":0,"IsInZone":false,"WallId":"string","Walkable":true,"ExhibitId":"string","HangingLightId":"string"},{"Id":"a53c8ee1-0dcf-4311-8fbd-a9432be619ae","XPosition":-8,"YPosition":-10,"TileSetNumber":7,"TileAtlasCoOrdinateX":0,"TileAtlasCoOrdinateY":0,"Layer":0,"IsInZone":false,"WallId":"string","Walkable":true,"ExhibitId":"string","HangingLightId":"string"},{"Id":"f7e48e98-3fef-4d49-b33f-c94e104d991f","XPosition":-8,"YPosition":-11,"TileSetNumber":7,"TileAtlasCoOrdinateX":0,"TileAtlasCoOrdinateY":0,"Layer":0,"IsInZone":false,"WallId":"string","Walkable":true,"ExhibitId":"string","HangingLightId":"string"},{"Id":"d095a230-4191-431b-9d10-10b48f070731","XPosition":-8,"YPosition":-12,"TileSetNumber":7,"TileAtlasCoOrdinateX":0,"TileAtlasCoOrdinateY":0,"Layer":0,"IsInZone":false,"WallId":"string","Walkable":true,"ExhibitId":"string","HangingLightId":"string"},{"Id":"d223ec3c-ffdf-4e48-b0cd-413de80db1ce","XPosition":-8,"YPosition":-13,"TileSetNumber":7,"TileAtlasCoOrdinateX":0,"TileAtlasCoOrdinateY":0,"Layer":0,"IsInZone":false,"WallId":"string","Walkable":true,"ExhibitId":"string","HangingLightId":"string"},{"Id":"8a0e6332-0e45-43d5-ae6a-161a3ebf5cc8","XPosition":-8,"YPosition":-14,"TileSetNumber":7,"TileAtlasCoOrdinateX":0,"TileAtlasCoOrdinateY":0,"Layer":0,"IsInZone":false,"WallId":"string","Walkable":true,"ExhibitId":"string","HangingLightId":"string"},{"Id":"3f17c568-d06b-472c-b1ee-84bc6f668f6b","XPosition":-8,"YPosition":-15,"TileSetNumber":7,"TileAtlasCoOrdinateX":0,"TileAtlasCoOrdinateY":0,"Layer":0,"IsInZone":false,"WallId":"string","Walkable":true,"ExhibitId":"string","HangingLightId":"string"},{"Id":"bf6d92a6-b550-4ceb-a544-47fda6e2aae2","XPosition":-8,"YPosition":-16,"TileSetNumber":7,"TileAtlasCoOrdinateX":0,"TileAtlasCoOrdinateY":0,"Layer":0,"IsInZone":false,"WallId":"string","Walkable":true,"ExhibitId":"string","HangingLightId":"string"},{"Id":"42561c2d-3bb6-4b3c-a8ef-ac3111928926","XPosition":-8,"YPosition":-17,"TileSetNumber":7,"TileAtlasCoOrdinateX":0,"TileAtlasCoOrdinateY":0,"Layer":0,"IsInZone":false,"WallId":"string","Walkable":true,"ExhibitId":"string","HangingLightId":"string"},{"Id":"37fd63af-4b42-4579-ad64-b08a7729ca14","XPosition":-8,"YPosition":-18,"TileSetNumber":7,"TileAtlasCoOrdinateX":0,"TileAtlasCoOrdinateY":0,"Layer":0,"IsInZone":false,"WallId":"string","Walkable":true,"ExhibitId":"string","HangingLightId":"string"},{"Id":"5c178f5e-85dd-4aec-8d24-4bec5841007f","XPosition":-8,"YPosition":-19,"TileSetNumber":7,"TileAtlasCoOrdinateX":0,"TileAtlasCoOrdinateY":0,"Layer":0,"IsInZone":false,"WallId":"basic_red_wallpaper","Walkable":true,"ExhibitId":"string","HangingLightId":"string"},{"Id":"7e6eaaf3-3dfb-4cf8-bd94-195fad77254c","XPosition":-9,"YPosition":0,"TileSetNumber":7,"TileAtlasCoOrdinateX":0,"TileAtlasCoOrdinateY":0,"Layer":0,"IsInZone":false,"WallId":"string","Walkable":false,"ExhibitId":"string","HangingLightId":"string"},{"Id":"b437b228-7b7e-43d6-bc80-57b2334f05ae","XPosition":-9,"YPosition":-1,"TileSetNumber":7,"TileAtlasCoOrdinateX":0,"TileAtlasCoOrdinateY":0,"Layer":0,"IsInZone":false,"WallId":"string","Walkable":true,"ExhibitId":"string","HangingLightId":"string"},{"Id":"1d6c44d8-89f3-4644-9892-3c18bb4131da","XPosition":-9,"YPosition":-2,"TileSetNumber":7,"TileAtlasCoOrdinateX":0,"TileAtlasCoOrdinateY":0,"Layer":0,"IsInZone":false,"WallId":"string","Walkable":true,"ExhibitId":"string","HangingLightId":"string"},{"Id":"bf7c2399-100b-43e0-b288-f1bd24f342dd","XPosition":-9,"YPosition":-3,"TileSetNumber":7,"TileAtlasCoOrdinateX":0,"TileAtlasCoOrdinateY":0,"Layer":0,"IsInZone":false,"WallId":"string","Walkable":true,"ExhibitId":"string","HangingLightId":"string"},{"Id":"71ce0328-050e-485e-9a1d-5906d5932827","XPosition":-9,"YPosition":-4,"TileSetNumber":7,"TileAtlasCoOrdinateX":0,"TileAtlasCoOrdinateY":0,"Layer":0,"IsInZone":false,"WallId":"string","Walkable":true,"ExhibitId":"string","HangingLightId":"string"},{"Id":"bb6df70b-479c-47a0-804c-f6f71cf489bd","XPosition":-9,"YPosition":-5,"TileSetNumber":7,"TileAtlasCoOrdinateX":0,"TileAtlasCoOrdinateY":0,"Layer":0,"IsInZone":false,"WallId":"string","Walkable":true,"ExhibitId":"string","HangingLightId":"string"},{"Id":"f5e234b6-a8ad-4e72-9fd6-f279b1835ab5","XPosition":-9,"YPosition":-6,"TileSetNumber":7,"TileAtlasCoOrdinateX":0,"TileAtlasCoOrdinateY":0,"Layer":0,"IsInZone":false,"WallId":"string","Walkable":true,"ExhibitId":"string","HangingLightId":"string"},{"Id":"cbf71617-2e7d-4952-868b-ad62f4964a33","XPosition":-9,"YPosition":-7,"TileSetNumber":7,"TileAtlasCoOrdinateX":0,"TileAtlasCoOrdinateY":0,"Layer":0,"IsInZone":false,"WallId":"string","Walkable":true,"ExhibitId":"string","HangingLightId":"string"},{"Id":"d87073a4-b3ac-479c-9b24-35900e775b96","XPosition":-9,"YPosition":-8,"TileSetNumber":7,"TileAtlasCoOrdinateX":0,"TileAtlasCoOrdinateY":0,"Layer":0,"IsInZone":false,"WallId":"string","Walkable":true,"ExhibitId":"string","HangingLightId":"string"},{"Id":"b53e66d0-c32c-49c4-8290-01445d3a33f3","XPosition":-9,"YPosition":-9,"TileSetNumber":7,"TileAtlasCoOrdinateX":0,"TileAtlasCoOrdinateY":0,"Layer":0,"IsInZone":false,"WallId":"string","Walkable":true,"ExhibitId":"string","HangingLightId":"string"},{"Id":"09a300d5-8a3d-4dfc-bea0-e066708fecdd","XPosition":-9,"YPosition":-10,"TileSetNumber":7,"TileAtlasCoOrdinateX":0,"TileAtlasCoOrdinateY":0,"Layer":0,"IsInZone":false,"WallId":"string","Walkable":true,"ExhibitId":"string","HangingLightId":"string"},{"Id":"2e1d0c9c-eea2-4d9d-b8c7-d7abb521058f","XPosition":-9,"YPosition":-11,"TileSetNumber":7,"TileAtlasCoOrdinateX":0,"TileAtlasCoOrdinateY":0,"Layer":0,"IsInZone":false,"WallId":"string","Walkable":true,"ExhibitId":"string","HangingLightId":"string"},{"Id":"c09fd85f-c60f-4ec9-8008-22383bcc0065","XPosition":-9,"YPosition":-12,"TileSetNumber":7,"TileAtlasCoOrdinateX":0,"TileAtlasCoOrdinateY":0,"Layer":0,"IsInZone":false,"WallId":"string","Walkable":true,"ExhibitId":"string","HangingLightId":"string"},{"Id":"d627cdf8-8d2a-4ed8-bf63-fbe1492c1d7f","XPosition":-9,"YPosition":-13,"TileSetNumber":7,"TileAtlasCoOrdinateX":0,"TileAtlasCoOrdinateY":0,"Layer":0,"IsInZone":false,"WallId":"string","Walkable":true,"ExhibitId":"string","HangingLightId":"string"},{"Id":"b2d3ed55-4474-41aa-8f87-29130faa330a","XPosition":-9,"YPosition":-14,"TileSetNumber":7,"TileAtlasCoOrdinateX":0,"TileAtlasCoOrdinateY":0,"Layer":0,"IsInZone":false,"WallId":"string","Walkable":true,"ExhibitId":"string","HangingLightId":"string"},{"Id":"1c338cf4-c7c1-4fa5-821e-05435047d46e","XPosition":-9,"YPosition":-15,"TileSetNumber":7,"TileAtlasCoOrdinateX":0,"TileAtlasCoOrdinateY":0,"Layer":0,"IsInZone":false,"WallId":"string","Walkable":true,"ExhibitId":"string","HangingLightId":"string"},{"Id":"790caf45-ee6a-4421-8938-8523cf50e094","XPosition":-9,"YPosition":-16,"TileSetNumber":7,"TileAtlasCoOrdinateX":0,"TileAtlasCoOrdinateY":0,"Layer":0,"IsInZone":false,"WallId":"string","Walkable":true,"ExhibitId":"string","HangingLightId":"string"},{"Id":"dd6c41c9-68bd-4c3e-a51e-92fb815643fa","XPosition":-9,"YPosition":-17,"TileSetNumber":7,"TileAtlasCoOrdinateX":0,"TileAtlasCoOrdinateY":0,"Layer":0,"IsInZone":false,"WallId":"string","Walkable":true,"ExhibitId":"string","HangingLightId":"string"},{"Id":"361fa6ac-67d0-4696-8349-97a3a2c2a661","XPosition":-9,"YPosition":-18,"TileSetNumber":7,"TileAtlasCoOrdinateX":0,"TileAtlasCoOrdinateY":0,"Layer":0,"IsInZone":false,"WallId":"string","Walkable":true,"ExhibitId":"string","HangingLightId":"string"},{"Id":"4acc519d-fc1b-4e49-a460-08daa6a8087a","XPosition":-9,"YPosition":-19,"TileSetNumber":7,"TileAtlasCoOrdinateX":0,"TileAtlasCoOrdinateY":0,"Layer":0,"IsInZone":false,"WallId":"basic_red_wallpaper","Walkable":true,"ExhibitId":"string","HangingLightId":"string"},{"Id":"ccc09c5f-8bc7-4ca9-8953-44c374fb9f6e","XPosition":-10,"YPosition":0,"TileSetNumber":7,"TileAtlasCoOrdinateX":0,"TileAtlasCoOrdinateY":0,"Layer":0,"IsInZone":false,"WallId":"string","Walkable":false,"ExhibitId":"string","HangingLightId":"string"},{"Id":"45065dfa-b940-4181-8c1e-7aa800dcb8ad","XPosition":-10,"YPosition":-1,"TileSetNumber":7,"TileAtlasCoOrdinateX":0,"TileAtlasCoOrdinateY":0,"Layer":0,"IsInZone":false,"WallId":"string","Walkable":true,"ExhibitId":"string","HangingLightId":"string"},{"Id":"796a61c4-76e6-43a3-9556-76b578cbf41a","XPosition":-10,"YPosition":-2,"TileSetNumber":7,"TileAtlasCoOrdinateX":0,"TileAtlasCoOrdinateY":0,"Layer":0,"IsInZone":false,"WallId":"string","Walkable":true,"ExhibitId":"string","HangingLightId":"string"},{"Id":"b2166048-ed9b-4b21-80bd-4992195b929a","XPosition":-10,"YPosition":-3,"TileSetNumber":7,"TileAtlasCoOrdinateX":0,"TileAtlasCoOrdinateY":0,"Layer":0,"IsInZone":false,"WallId":"string","Walkable":true,"ExhibitId":"string","HangingLightId":"string"},{"Id":"7b2c2da4-80a1-4821-a3e8-620fd5e098f3","XPosition":-10,"YPosition":-4,"TileSetNumber":7,"TileAtlasCoOrdinateX":0,"TileAtlasCoOrdinateY":0,"Layer":0,"IsInZone":false,"WallId":"string","Walkable":true,"ExhibitId":"string","HangingLightId":"string"},{"Id":"3926251d-e7d6-439e-ae55-089447c1ffe8","XPosition":-10,"YPosition":-5,"TileSetNumber":7,"TileAtlasCoOrdinateX":0,"TileAtlasCoOrdinateY":0,"Layer":0,"IsInZone":false,"WallId":"string","Walkable":true,"ExhibitId":"string","HangingLightId":"string"},{"Id":"8daa5274-8589-43f9-9b63-ed8959dd2cf4","XPosition":-10,"YPosition":-6,"TileSetNumber":7,"TileAtlasCoOrdinateX":0,"TileAtlasCoOrdinateY":0,"Layer":0,"IsInZone":false,"WallId":"string","Walkable":true,"ExhibitId":"string","HangingLightId":"string"},{"Id":"09548459-84b6-47dc-8c26-86ad23c5cfb1","XPosition":-10,"YPosition":-7,"TileSetNumber":7,"TileAtlasCoOrdinateX":0,"TileAtlasCoOrdinateY":0,"Layer":0,"IsInZone":false,"WallId":"string","Walkable":true,"ExhibitId":"string","HangingLightId":"string"},{"Id":"7b6cb81a-3ade-4500-a617-a53284622d89","XPosition":-10,"YPosition":-8,"TileSetNumber":7,"TileAtlasCoOrdinateX":0,"TileAtlasCoOrdinateY":0,"Layer":0,"IsInZone":false,"WallId":"string","Walkable":true,"ExhibitId":"string","HangingLightId":"string"},{"Id":"2fb4d445-6946-40b5-89a7-ca8c54685222","XPosition":-10,"YPosition":-9,"TileSetNumber":7,"TileAtlasCoOrdinateX":0,"TileAtlasCoOrdinateY":0,"Layer":0,"IsInZone":false,"WallId":"string","Walkable":true,"ExhibitId":"string","HangingLightId":"string"},{"Id":"5be73424-cd70-43c2-87f8-ce1057f5d037","XPosition":-10,"YPosition":-10,"TileSetNumber":7,"TileAtlasCoOrdinateX":0,"TileAtlasCoOrdinateY":0,"Layer":0,"IsInZone":false,"WallId":"string","Walkable":true,"ExhibitId":"string","HangingLightId":"string"},{"Id":"2b04d075-b053-4deb-afa3-f4b35de3becb","XPosition":-10,"YPosition":-11,"TileSetNumber":7,"TileAtlasCoOrdinateX":0,"TileAtlasCoOrdinateY":0,"Layer":0,"IsInZone":false,"WallId":"string","Walkable":true,"ExhibitId":"string","HangingLightId":"string"},{"Id":"bfb843ba-9b7b-4785-8b42-ef5bccd28c90","XPosition":-10,"YPosition":-12,"TileSetNumber":7,"TileAtlasCoOrdinateX":0,"TileAtlasCoOrdinateY":0,"Layer":0,"IsInZone":false,"WallId":"string","Walkable":true,"ExhibitId":"string","HangingLightId":"string"},{"Id":"fe2661d4-0b56-4ba7-9e65-7c11e6a6773d","XPosition":-10,"YPosition":-13,"TileSetNumber":7,"TileAtlasCoOrdinateX":0,"TileAtlasCoOrdinateY":0,"Layer":0,"IsInZone":false,"WallId":"string","Walkable":true,"ExhibitId":"string","HangingLightId":"string"},{"Id":"aebe26f0-090d-424d-858d-336c7a869356","XPosition":-10,"YPosition":-14,"TileSetNumber":7,"TileAtlasCoOrdinateX":0,"TileAtlasCoOrdinateY":0,"Layer":0,"IsInZone":false,"WallId":"string","Walkable":true,"ExhibitId":"string","HangingLightId":"string"},{"Id":"0aec517c-ea56-4ad0-8c85-5a069b45a735","XPosition":-10,"YPosition":-15,"TileSetNumber":7,"TileAtlasCoOrdinateX":0,"TileAtlasCoOrdinateY":0,"Layer":0,"IsInZone":false,"WallId":"string","Walkable":true,"ExhibitId":"string","HangingLightId":"string"},{"Id":"ac7e6eda-0255-42a5-95d2-8a485766d897","XPosition":-10,"YPosition":-16,"TileSetNumber":7,"TileAtlasCoOrdinateX":0,"TileAtlasCoOrdinateY":0,"Layer":0,"IsInZone":false,"WallId":"string","Walkable":true,"ExhibitId":"string","HangingLightId":"string"},{"Id":"56e4f7b2-8774-4c7e-93e2-ab3c90ebc71c","XPosition":-10,"YPosition":-17,"TileSetNumber":7,"TileAtlasCoOrdinateX":0,"TileAtlasCoOrdinateY":0,"Layer":0,"IsInZone":false,"WallId":"string","Walkable":true,"ExhibitId":"string","HangingLightId":"string"},{"Id":"0d4ae285-1d0f-4267-a272-b657e02eac35","XPosition":-10,"YPosition":-18,"TileSetNumber":7,"TileAtlasCoOrdinateX":0,"TileAtlasCoOrdinateY":0,"Layer":0,"IsInZone":false,"WallId":"string","Walkable":true,"ExhibitId":"string","HangingLightId":"string"},{"Id":"2ff0dcb9-f579-4b4d-8563-2b5106ec1d39","XPosition":-10,"YPosition":-19,"TileSetNumber":7,"TileAtlasCoOrdinateX":0,"TileAtlasCoOrdinateY":0,"Layer":0,"IsInZone":false,"WallId":"basic_red_wallpaper","Walkable":true,"ExhibitId":"string","HangingLightId":"string"},{"Id":"915c30e6-57ed-4a27-b38e-1f1d7b3368f1","XPosition":-11,"YPosition":0,"TileSetNumber":7,"TileAtlasCoOrdinateX":0,"TileAtlasCoOrdinateY":0,"Layer":0,"IsInZone":false,"WallId":"string","Walkable":false,"ExhibitId":"string","HangingLightId":"string"},{"Id":"a67b240a-edc2-4ed2-bfdb-68c9e743290f","XPosition":-11,"YPosition":-1,"TileSetNumber":7,"TileAtlasCoOrdinateX":0,"TileAtlasCoOrdinateY":0,"Layer":0,"IsInZone":false,"WallId":"string","Walkable":true,"ExhibitId":"string","HangingLightId":"string"},{"Id":"f83bb674-72ae-46d2-97a7-401a052e85cc","XPosition":-11,"YPosition":-2,"TileSetNumber":7,"TileAtlasCoOrdinateX":0,"TileAtlasCoOrdinateY":0,"Layer":0,"IsInZone":false,"WallId":"string","Walkable":true,"ExhibitId":"string","HangingLightId":"string"},{"Id":"beb5b6f1-0dc5-4423-ae13-96e51b27d9a3","XPosition":-11,"YPosition":-3,"TileSetNumber":7,"TileAtlasCoOrdinateX":0,"TileAtlasCoOrdinateY":0,"Layer":0,"IsInZone":false,"WallId":"string","Walkable":true,"ExhibitId":"string","HangingLightId":"string"},{"Id":"3416be94-4ec2-459b-99a6-48cadfbfa85e","XPosition":-11,"YPosition":-4,"TileSetNumber":7,"TileAtlasCoOrdinateX":0,"TileAtlasCoOrdinateY":0,"Layer":0,"IsInZone":false,"WallId":"string","Walkable":true,"ExhibitId":"string","HangingLightId":"string"},{"Id":"e7068a26-f1fd-4023-8295-0b15a2ed02b6","XPosition":-11,"YPosition":-5,"TileSetNumber":7,"TileAtlasCoOrdinateX":0,"TileAtlasCoOrdinateY":0,"Layer":0,"IsInZone":false,"WallId":"string","Walkable":true,"ExhibitId":"string","HangingLightId":"string"},{"Id":"1e799085-2351-43b4-8bab-cad6c76800a2","XPosition":-11,"YPosition":-6,"TileSetNumber":7,"TileAtlasCoOrdinateX":0,"TileAtlasCoOrdinateY":0,"Layer":0,"IsInZone":false,"WallId":"string","Walkable":true,"ExhibitId":"string","HangingLightId":"string"},{"Id":"b5e6aaab-703f-450f-860d-70d332509fee","XPosition":-11,"YPosition":-7,"TileSetNumber":7,"TileAtlasCoOrdinateX":0,"TileAtlasCoOrdinateY":0,"Layer":0,"IsInZone":false,"WallId":"string","Walkable":true,"ExhibitId":"string","HangingLightId":"string"},{"Id":"5781d768-0808-460e-86ce-eec3a5360b59","XPosition":-11,"YPosition":-8,"TileSetNumber":7,"TileAtlasCoOrdinateX":0,"TileAtlasCoOrdinateY":0,"Layer":0,"IsInZone":false,"WallId":"string","Walkable":true,"ExhibitId":"string","HangingLightId":"string"},{"Id":"ae10162c-e7f2-4e00-8baa-a29d6d8e5ddc","XPosition":-11,"YPosition":-9,"TileSetNumber":7,"TileAtlasCoOrdinateX":0,"TileAtlasCoOrdinateY":0,"Layer":0,"IsInZone":false,"WallId":"string","Walkable":true,"ExhibitId":"string","HangingLightId":"string"},{"Id":"2993f731-40f6-423c-8fed-b27b413588bb","XPosition":-11,"YPosition":-10,"TileSetNumber":7,"TileAtlasCoOrdinateX":0,"TileAtlasCoOrdinateY":0,"Layer":0,"IsInZone":false,"WallId":"string","Walkable":true,"ExhibitId":"string","HangingLightId":"string"},{"Id":"0052a492-1f80-4ebf-98a8-8783ee87183e","XPosition":-11,"YPosition":-11,"TileSetNumber":7,"TileAtlasCoOrdinateX":0,"TileAtlasCoOrdinateY":0,"Layer":0,"IsInZone":false,"WallId":"string","Walkable":true,"ExhibitId":"string","HangingLightId":"string"},{"Id":"36f63f7e-cd58-4e06-93a6-b40ab9680241","XPosition":-11,"YPosition":-12,"TileSetNumber":7,"TileAtlasCoOrdinateX":0,"TileAtlasCoOrdinateY":0,"Layer":0,"IsInZone":false,"WallId":"string","Walkable":true,"ExhibitId":"string","HangingLightId":"string"},{"Id":"be1da5d8-44a9-4dcc-8371-68da8f2e2625","XPosition":-11,"YPosition":-13,"TileSetNumber":7,"TileAtlasCoOrdinateX":0,"TileAtlasCoOrdinateY":0,"Layer":0,"IsInZone":false,"WallId":"string","Walkable":true,"ExhibitId":"string","HangingLightId":"string"},{"Id":"6c55e81f-2708-4c21-b1b7-c7ec6bf128c2","XPosition":-11,"YPosition":-14,"TileSetNumber":7,"TileAtlasCoOrdinateX":0,"TileAtlasCoOrdinateY":0,"Layer":0,"IsInZone":false,"WallId":"string","Walkable":true,"ExhibitId":"string","HangingLightId":"string"},{"Id":"bdf5f0d2-3faf-4dbf-9017-1be531feede5","XPosition":-11,"YPosition":-15,"TileSetNumber":7,"TileAtlasCoOrdinateX":0,"TileAtlasCoOrdinateY":0,"Layer":0,"IsInZone":false,"WallId":"string","Walkable":true,"ExhibitId":"string","HangingLightId":"string"},{"Id":"5258a9e1-ee1e-49f6-a63d-117afe2fea05","XPosition":-11,"YPosition":-16,"TileSetNumber":7,"TileAtlasCoOrdinateX":0,"TileAtlasCoOrdinateY":0,"Layer":0,"IsInZone":false,"WallId":"string","Walkable":true,"ExhibitId":"string","HangingLightId":"string"},{"Id":"142708d4-27d4-4f0c-88b7-afc25166d59d","XPosition":-11,"YPosition":-17,"TileSetNumber":7,"TileAtlasCoOrdinateX":0,"TileAtlasCoOrdinateY":0,"Layer":0,"IsInZone":false,"WallId":"string","Walkable":true,"ExhibitId":"string","HangingLightId":"string"},{"Id":"b36f1b0b-6e05-4d8f-8f4a-b1c305a11b9a","XPosition":-11,"YPosition":-18,"TileSetNumber":7,"TileAtlasCoOrdinateX":0,"TileAtlasCoOrdinateY":0,"Layer":0,"IsInZone":false,"WallId":"string","Walkable":true,"ExhibitId":"string","HangingLightId":"string"},{"Id":"8ac96778-936d-462c-a2cb-93af8db57a77","XPosition":-11,"YPosition":-19,"TileSetNumber":7,"TileAtlasCoOrdinateX":0,"TileAtlasCoOrdinateY":0,"Layer":0,"IsInZone":false,"WallId":"basic_red_wallpaper","Walkable":true,"ExhibitId":"string","HangingLightId":"string"},{"Id":"445ffdc6-733b-40b7-a336-6f7de3df3b92","XPosition":-12,"YPosition":0,"TileSetNumber":7,"TileAtlasCoOrdinateX":0,"TileAtlasCoOrdinateY":0,"Layer":0,"IsInZone":false,"WallId":"string","Walkable":false,"ExhibitId":"string","HangingLightId":"string"},{"Id":"23f03a3f-82e9-4442-bb36-2823662e748e","XPosition":-12,"YPosition":-1,"TileSetNumber":7,"TileAtlasCoOrdinateX":0,"TileAtlasCoOrdinateY":0,"Layer":0,"IsInZone":false,"WallId":"string","Walkable":true,"ExhibitId":"string","HangingLightId":"string"},{"Id":"4676674a-58e5-4366-aed3-b99c3816fd10","XPosition":-12,"YPosition":-2,"TileSetNumber":7,"TileAtlasCoOrdinateX":0,"TileAtlasCoOrdinateY":0,"Layer":0,"IsInZone":false,"WallId":"string","Walkable":true,"ExhibitId":"string","HangingLightId":"string"},{"Id":"0f7aa0cb-fe3a-4ef8-a28e-36a9809f79f9","XPosition":-12,"YPosition":-3,"TileSetNumber":7,"TileAtlasCoOrdinateX":0,"TileAtlasCoOrdinateY":0,"Layer":0,"IsInZone":false,"WallId":"string","Walkable":true,"ExhibitId":"string","HangingLightId":"string"},{"Id":"9c904cad-ef7e-431b-a7d0-1b60d79fdddf","XPosition":-12,"YPosition":-4,"TileSetNumber":7,"TileAtlasCoOrdinateX":0,"TileAtlasCoOrdinateY":0,"Layer":0,"IsInZone":false,"WallId":"string","Walkable":true,"ExhibitId":"string","HangingLightId":"string"},{"Id":"40d4b6ed-56ce-45b0-a622-962d11f82a32","XPosition":-12,"YPosition":-5,"TileSetNumber":7,"TileAtlasCoOrdinateX":0,"TileAtlasCoOrdinateY":0,"Layer":0,"IsInZone":false,"WallId":"string","Walkable":true,"ExhibitId":"string","HangingLightId":"string"},{"Id":"c804509d-97ef-4704-be22-9ceddf3e3c22","XPosition":-12,"YPosition":-6,"TileSetNumber":7,"TileAtlasCoOrdinateX":0,"TileAtlasCoOrdinateY":0,"Layer":0,"IsInZone":false,"WallId":"string","Walkable":true,"ExhibitId":"string","HangingLightId":"string"},{"Id":"1dcc8ab3-4841-44ba-a762-6f143a15aa15","XPosition":-12,"YPosition":-7,"TileSetNumber":7,"TileAtlasCoOrdinateX":0,"TileAtlasCoOrdinateY":0,"Layer":0,"IsInZone":false,"WallId":"string","Walkable":true,"ExhibitId":"string","HangingLightId":"string"},{"Id":"ceca082a-d6a5-4cd2-9fcd-d929a4515a80","XPosition":-12,"YPosition":-8,"TileSetNumber":7,"TileAtlasCoOrdinateX":0,"TileAtlasCoOrdinateY":0,"Layer":0,"IsInZone":false,"WallId":"string","Walkable":true,"ExhibitId":"string","HangingLightId":"string"},{"Id":"4821c03d-a382-4838-94ef-d762b802b7eb","XPosition":-12,"YPosition":-9,"TileSetNumber":7,"TileAtlasCoOrdinateX":0,"TileAtlasCoOrdinateY":0,"Layer":0,"IsInZone":false,"WallId":"string","Walkable":true,"ExhibitId":"string","HangingLightId":"string"},{"Id":"27d197b5-3fae-4f39-9941-c8581ff02b3a","XPosition":-12,"YPosition":-10,"TileSetNumber":7,"TileAtlasCoOrdinateX":0,"TileAtlasCoOrdinateY":0,"Layer":0,"IsInZone":false,"WallId":"string","Walkable":true,"ExhibitId":"string","HangingLightId":"string"},{"Id":"366cb9e4-1f78-4f0e-b665-3a19d5ea17c1","XPosition":-12,"YPosition":-11,"TileSetNumber":7,"TileAtlasCoOrdinateX":0,"TileAtlasCoOrdinateY":0,"Layer":0,"IsInZone":false,"WallId":"string","Walkable":true,"ExhibitId":"string","HangingLightId":"string"},{"Id":"5f5e281e-215d-44a2-8a44-9fbdb859c936","XPosition":-12,"YPosition":-12,"TileSetNumber":7,"TileAtlasCoOrdinateX":0,"TileAtlasCoOrdinateY":0,"Layer":0,"IsInZone":false,"WallId":"string","Walkable":true,"ExhibitId":"string","HangingLightId":"string"},{"Id":"49a62a86-9bc3-43bb-b1cb-9ce567b070bb","XPosition":-12,"YPosition":-13,"TileSetNumber":7,"TileAtlasCoOrdinateX":0,"TileAtlasCoOrdinateY":0,"Layer":0,"IsInZone":false,"WallId":"string","Walkable":true,"ExhibitId":"string","HangingLightId":"string"},{"Id":"be3f5f24-1b12-4ef2-839f-89759e241dba","XPosition":-12,"YPosition":-14,"TileSetNumber":7,"TileAtlasCoOrdinateX":0,"TileAtlasCoOrdinateY":0,"Layer":0,"IsInZone":false,"WallId":"string","Walkable":true,"ExhibitId":"string","HangingLightId":"string"},{"Id":"4d8d2bd6-2a97-4b57-afa7-754875c24e61","XPosition":-12,"YPosition":-15,"TileSetNumber":7,"TileAtlasCoOrdinateX":0,"TileAtlasCoOrdinateY":0,"Layer":0,"IsInZone":false,"WallId":"string","Walkable":true,"ExhibitId":"string","HangingLightId":"string"},{"Id":"606c8239-a165-4fa6-828c-74a46568d59d","XPosition":-12,"YPosition":-16,"TileSetNumber":7,"TileAtlasCoOrdinateX":0,"TileAtlasCoOrdinateY":0,"Layer":0,"IsInZone":false,"WallId":"string","Walkable":true,"ExhibitId":"string","HangingLightId":"string"},{"Id":"b85af1d3-a70c-490f-b34d-71197157a900","XPosition":-12,"YPosition":-17,"TileSetNumber":7,"TileAtlasCoOrdinateX":0,"TileAtlasCoOrdinateY":0,"Layer":0,"IsInZone":false,"WallId":"string","Walkable":true,"ExhibitId":"string","HangingLightId":"string"},{"Id":"c0c2d55c-6df0-44ab-9cd0-5170b63b6f73","XPosition":-12,"YPosition":-18,"TileSetNumber":7,"TileAtlasCoOrdinateX":0,"TileAtlasCoOrdinateY":0,"Layer":0,"IsInZone":false,"WallId":"string","Walkable":true,"ExhibitId":"string","HangingLightId":"string"},{"Id":"5d1a7aa5-24fc-444b-9948-6e6f13d29fdc","XPosition":-12,"YPosition":-19,"TileSetNumber":7,"TileAtlasCoOrdinateX":0,"TileAtlasCoOrdinateY":0,"Layer":0,"IsInZone":false,"WallId":"basic_red_wallpaper","Walkable":true,"ExhibitId":"string","HangingLightId":"string"},{"Id":"0c2f0dd6-4bc2-48a9-86b3-1b5d184aa3c4","XPosition":-13,"YPosition":0,"TileSetNumber":7,"TileAtlasCoOrdinateX":0,"TileAtlasCoOrdinateY":0,"Layer":0,"IsInZone":false,"WallId":"string","Walkable":false,"ExhibitId":"string","HangingLightId":"string"},{"Id":"1199466d-b65a-42d2-8136-5edfc1734aea","XPosition":-13,"YPosition":-1,"TileSetNumber":7,"TileAtlasCoOrdinateX":0,"TileAtlasCoOrdinateY":0,"Layer":0,"IsInZone":false,"WallId":"string","Walkable":true,"ExhibitId":"string","HangingLightId":"string"},{"Id":"bb910d77-9a6a-4441-af64-040d9355fa60","XPosition":-13,"YPosition":-2,"TileSetNumber":7,"TileAtlasCoOrdinateX":0,"TileAtlasCoOrdinateY":0,"Layer":0,"IsInZone":false,"WallId":"string","Walkable":true,"ExhibitId":"string","HangingLightId":"string"},{"Id":"24526541-2a2a-44a3-bd30-8948d867018d","XPosition":-13,"YPosition":-3,"TileSetNumber":7,"TileAtlasCoOrdinateX":0,"TileAtlasCoOrdinateY":0,"Layer":0,"IsInZone":false,"WallId":"string","Walkable":true,"ExhibitId":"string","HangingLightId":"string"},{"Id":"97acc076-9092-4b7c-be14-b387851d0973","XPosition":-13,"YPosition":-4,"TileSetNumber":7,"TileAtlasCoOrdinateX":0,"TileAtlasCoOrdinateY":0,"Layer":0,"IsInZone":false,"WallId":"string","Walkable":true,"ExhibitId":"string","HangingLightId":"string"},{"Id":"de2086b7-1128-4198-a3b6-d05d4a009996","XPosition":-13,"YPosition":-5,"TileSetNumber":7,"TileAtlasCoOrdinateX":0,"TileAtlasCoOrdinateY":0,"Layer":0,"IsInZone":false,"WallId":"string","Walkable":true,"ExhibitId":"string","HangingLightId":"string"},{"Id":"0a34b53e-41cf-4378-b6c5-a6b146ef7289","XPosition":-13,"YPosition":-6,"TileSetNumber":7,"TileAtlasCoOrdinateX":0,"TileAtlasCoOrdinateY":0,"Layer":0,"IsInZone":false,"WallId":"string","Walkable":true,"ExhibitId":"string","HangingLightId":"string"},{"Id":"4bfea133-f042-43a3-90b7-484dd431529a","XPosition":-13,"YPosition":-7,"TileSetNumber":7,"TileAtlasCoOrdinateX":0,"TileAtlasCoOrdinateY":0,"Layer":0,"IsInZone":false,"WallId":"string","Walkable":true,"ExhibitId":"string","HangingLightId":"string"},{"Id":"cd90e89c-a9bf-46f1-894b-e69c90255191","XPosition":-13,"YPosition":-8,"TileSetNumber":7,"TileAtlasCoOrdinateX":0,"TileAtlasCoOrdinateY":0,"Layer":0,"IsInZone":false,"WallId":"string","Walkable":true,"ExhibitId":"string","HangingLightId":"string"},{"Id":"a6703a42-e97b-4c53-8622-beec452d8a35","XPosition":-13,"YPosition":-9,"TileSetNumber":7,"TileAtlasCoOrdinateX":0,"TileAtlasCoOrdinateY":0,"Layer":0,"IsInZone":false,"WallId":"string","Walkable":true,"ExhibitId":"string","HangingLightId":"string"},{"Id":"aa8a9689-c28f-4361-a35d-40fead0ae049","XPosition":-13,"YPosition":-10,"TileSetNumber":7,"TileAtlasCoOrdinateX":0,"TileAtlasCoOrdinateY":0,"Layer":0,"IsInZone":false,"WallId":"string","Walkable":true,"ExhibitId":"string","HangingLightId":"string"},{"Id":"45597265-0472-4cee-b382-49b3a423aaaf","XPosition":-13,"YPosition":-11,"TileSetNumber":7,"TileAtlasCoOrdinateX":0,"TileAtlasCoOrdinateY":0,"Layer":0,"IsInZone":false,"WallId":"string","Walkable":true,"ExhibitId":"string","HangingLightId":"string"},{"Id":"90083bdd-c362-49da-bd0a-bba607ba1c64","XPosition":-13,"YPosition":-12,"TileSetNumber":7,"TileAtlasCoOrdinateX":0,"TileAtlasCoOrdinateY":0,"Layer":0,"IsInZone":false,"WallId":"string","Walkable":true,"ExhibitId":"string","HangingLightId":"string"},{"Id":"87ae3cd5-591d-4ee4-bf93-847d9083a43a","XPosition":-13,"YPosition":-13,"TileSetNumber":7,"TileAtlasCoOrdinateX":0,"TileAtlasCoOrdinateY":0,"Layer":0,"IsInZone":false,"WallId":"string","Walkable":true,"ExhibitId":"string","HangingLightId":"string"},{"Id":"f8076eda-96da-47c0-bc7a-36ba9f214b32","XPosition":-13,"YPosition":-14,"TileSetNumber":7,"TileAtlasCoOrdinateX":0,"TileAtlasCoOrdinateY":0,"Layer":0,"IsInZone":false,"WallId":"string","Walkable":true,"ExhibitId":"string","HangingLightId":"string"},{"Id":"68295911-b27a-40aa-935d-9a97c8a8a23c","XPosition":-13,"YPosition":-15,"TileSetNumber":7,"TileAtlasCoOrdinateX":0,"TileAtlasCoOrdinateY":0,"Layer":0,"IsInZone":false,"WallId":"string","Walkable":true,"ExhibitId":"string","HangingLightId":"string"},{"Id":"2955e0ce-0e8e-46ee-9034-1e98b62b3569","XPosition":-13,"YPosition":-16,"TileSetNumber":7,"TileAtlasCoOrdinateX":0,"TileAtlasCoOrdinateY":0,"Layer":0,"IsInZone":false,"WallId":"string","Walkable":true,"ExhibitId":"string","HangingLightId":"string"},{"Id":"778a2446-73cf-4858-ab42-1081f865ab0c","XPosition":-13,"YPosition":-17,"TileSetNumber":7,"TileAtlasCoOrdinateX":0,"TileAtlasCoOrdinateY":0,"Layer":0,"IsInZone":false,"WallId":"string","Walkable":true,"ExhibitId":"string","HangingLightId":"string"},{"Id":"4195cd1f-1ad3-4942-88db-fb22e68051fc","XPosition":-13,"YPosition":-18,"TileSetNumber":7,"TileAtlasCoOrdinateX":0,"TileAtlasCoOrdinateY":0,"Layer":0,"IsInZone":false,"WallId":"string","Walkable":true,"ExhibitId":"string","HangingLightId":"string"},{"Id":"1c7488ea-8f10-42f6-9fdf-a3ce356c16cc","XPosition":-13,"YPosition":-19,"TileSetNumber":7,"TileAtlasCoOrdinateX":0,"TileAtlasCoOrdinateY":0,"Layer":0,"IsInZone":false,"WallId":"basic_red_wallpaper","Walkable":true,"ExhibitId":"string","HangingLightId":"string"},{"Id":"4da5a86a-258e-44d3-aade-7e2bbff5a254","XPosition":-14,"YPosition":0,"TileSetNumber":7,"TileAtlasCoOrdinateX":0,"TileAtlasCoOrdinateY":0,"Layer":0,"IsInZone":false,"WallId":"string","Walkable":false,"ExhibitId":"string","HangingLightId":"string"},{"Id":"8410fe53-c6ff-4f38-8869-2203bfbac393","XPosition":-14,"YPosition":-1,"TileSetNumber":7,"TileAtlasCoOrdinateX":0,"TileAtlasCoOrdinateY":0,"Layer":0,"IsInZone":false,"WallId":"string","Walkable":true,"ExhibitId":"string","HangingLightId":"string"},{"Id":"72d4819c-f6c3-469b-ba29-142a9adf4461","XPosition":-14,"YPosition":-2,"TileSetNumber":7,"TileAtlasCoOrdinateX":0,"TileAtlasCoOrdinateY":0,"Layer":0,"IsInZone":false,"WallId":"string","Walkable":true,"ExhibitId":"string","HangingLightId":"string"},{"Id":"1c7f44cc-00b4-4f73-9cb5-6ee3b68259e9","XPosition":-14,"YPosition":-3,"TileSetNumber":7,"TileAtlasCoOrdinateX":0,"TileAtlasCoOrdinateY":0,"Layer":0,"IsInZone":false,"WallId":"string","Walkable":true,"ExhibitId":"string","HangingLightId":"string"},{"Id":"bb18ea06-4f46-470a-9e72-c8a409b933e5","XPosition":-14,"YPosition":-4,"TileSetNumber":7,"TileAtlasCoOrdinateX":0,"TileAtlasCoOrdinateY":0,"Layer":0,"IsInZone":false,"WallId":"string","Walkable":true,"ExhibitId":"string","HangingLightId":"string"},{"Id":"43ab9078-eb98-4a09-a4d5-96b0f7dc7833","XPosition":-14,"YPosition":-5,"TileSetNumber":7,"TileAtlasCoOrdinateX":0,"TileAtlasCoOrdinateY":0,"Layer":0,"IsInZone":false,"WallId":"string","Walkable":true,"ExhibitId":"string","HangingLightId":"string"},{"Id":"a0d0ab7b-d17c-4381-84a5-b63f6fe5a14e","XPosition":-14,"YPosition":-6,"TileSetNumber":7,"TileAtlasCoOrdinateX":0,"TileAtlasCoOrdinateY":0,"Layer":0,"IsInZone":false,"WallId":"string","Walkable":true,"ExhibitId":"string","HangingLightId":"string"},{"Id":"90e7a056-6af2-4854-b911-076aebbf0a33","XPosition":-14,"YPosition":-7,"TileSetNumber":7,"TileAtlasCoOrdinateX":0,"TileAtlasCoOrdinateY":0,"Layer":0,"IsInZone":false,"WallId":"string","Walkable":true,"ExhibitId":"string","HangingLightId":"string"},{"Id":"7ff26daa-eb37-4b22-b0fd-767b1430dd97","XPosition":-14,"YPosition":-8,"TileSetNumber":7,"TileAtlasCoOrdinateX":0,"TileAtlasCoOrdinateY":0,"Layer":0,"IsInZone":false,"WallId":"string","Walkable":true,"ExhibitId":"string","HangingLightId":"string"},{"Id":"10011961-cbfd-4928-9588-aa507fa6f15f","XPosition":-14,"YPosition":-9,"TileSetNumber":7,"TileAtlasCoOrdinateX":0,"TileAtlasCoOrdinateY":0,"Layer":0,"IsInZone":false,"WallId":"string","Walkable":true,"ExhibitId":"string","HangingLightId":"string"},{"Id":"6aea02eb-14fd-4f5a-9ad9-6b3e5a2bc42a","XPosition":-14,"YPosition":-10,"TileSetNumber":7,"TileAtlasCoOrdinateX":0,"TileAtlasCoOrdinateY":0,"Layer":0,"IsInZone":false,"WallId":"string","Walkable":true,"ExhibitId":"string","HangingLightId":"string"},{"Id":"a3f91c2a-7729-498b-93a0-74845445ade1","XPosition":-14,"YPosition":-11,"TileSetNumber":7,"TileAtlasCoOrdinateX":0,"TileAtlasCoOrdinateY":0,"Layer":0,"IsInZone":false,"WallId":"string","Walkable":true,"ExhibitId":"string","HangingLightId":"string"},{"Id":"8e698345-50e7-4e77-871b-44ade7895f57","XPosition":-14,"YPosition":-12,"TileSetNumber":7,"TileAtlasCoOrdinateX":0,"TileAtlasCoOrdinateY":0,"Layer":0,"IsInZone":false,"WallId":"string","Walkable":true,"ExhibitId":"string","HangingLightId":"string"},{"Id":"686f3bed-fe27-42db-bef1-39dd92891fcb","XPosition":-14,"YPosition":-13,"TileSetNumber":7,"TileAtlasCoOrdinateX":0,"TileAtlasCoOrdinateY":0,"Layer":0,"IsInZone":false,"WallId":"string","Walkable":true,"ExhibitId":"string","HangingLightId":"string"},{"Id":"121ad1c6-2cc2-43d2-bfcc-95cab386b9cd","XPosition":-14,"YPosition":-14,"TileSetNumber":7,"TileAtlasCoOrdinateX":0,"TileAtlasCoOrdinateY":0,"Layer":0,"IsInZone":false,"WallId":"string","Walkable":true,"ExhibitId":"string","HangingLightId":"string"},{"Id":"fb3d782c-9c19-4e86-a64b-7960b426f2bb","XPosition":-14,"YPosition":-15,"TileSetNumber":7,"TileAtlasCoOrdinateX":0,"TileAtlasCoOrdinateY":0,"Layer":0,"IsInZone":false,"WallId":"string","Walkable":true,"ExhibitId":"string","HangingLightId":"string"},{"Id":"146c3342-c612-4bb1-b686-402652fa617f","XPosition":-14,"YPosition":-16,"TileSetNumber":7,"TileAtlasCoOrdinateX":0,"TileAtlasCoOrdinateY":0,"Layer":0,"IsInZone":false,"WallId":"string","Walkable":true,"ExhibitId":"string","HangingLightId":"string"},{"Id":"d9541a9a-8aa2-4d86-aee8-f4b19bb91081","XPosition":-14,"YPosition":-17,"TileSetNumber":7,"TileAtlasCoOrdinateX":0,"TileAtlasCoOrdinateY":0,"Layer":0,"IsInZone":false,"WallId":"string","Walkable":true,"ExhibitId":"string","HangingLightId":"string"},{"Id":"6c61b839-5ab6-4ef4-8380-8bdcf36037ee","XPosition":-14,"YPosition":-18,"TileSetNumber":7,"TileAtlasCoOrdinateX":0,"TileAtlasCoOrdinateY":0,"Layer":0,"IsInZone":false,"WallId":"string","Walkable":true,"ExhibitId":"string","HangingLightId":"string"},{"Id":"42e5ec27-d0e3-47fe-8d97-15dffd90ec35","XPosition":-14,"YPosition":-19,"TileSetNumber":7,"TileAtlasCoOrdinateX":0,"TileAtlasCoOrdinateY":0,"Layer":0,"IsInZone":false,"WallId":"basic_red_wallpaper","Walkable":true,"ExhibitId":"string","HangingLightId":"string"},{"Id":"1801eb28-3fe6-487f-9279-da8d93f6f4f6","XPosition":-15,"YPosition":0,"TileSetNumber":7,"TileAtlasCoOrdinateX":0,"TileAtlasCoOrdinateY":0,"Layer":0,"IsInZone":false,"WallId":"string","Walkable":false,"ExhibitId":"string","HangingLightId":"string"},{"Id":"eb2494b5-4e56-45eb-9484-74b2350c1850","XPosition":-15,"YPosition":-1,"TileSetNumber":7,"TileAtlasCoOrdinateX":0,"TileAtlasCoOrdinateY":0,"Layer":0,"IsInZone":false,"WallId":"string","Walkable":true,"ExhibitId":"string","HangingLightId":"string"},{"Id":"8d211de5-37a7-46f4-8875-3a98eaad5cf4","XPosition":-15,"YPosition":-2,"TileSetNumber":7,"TileAtlasCoOrdinateX":0,"TileAtlasCoOrdinateY":0,"Layer":0,"IsInZone":false,"WallId":"string","Walkable":true,"ExhibitId":"string","HangingLightId":"string"},{"Id":"de4f2d20-c609-40eb-a57d-cfd2e2a1617a","XPosition":-15,"YPosition":-3,"TileSetNumber":7,"TileAtlasCoOrdinateX":0,"TileAtlasCoOrdinateY":0,"Layer":0,"IsInZone":false,"WallId":"string","Walkable":true,"ExhibitId":"string","HangingLightId":"string"},{"Id":"29a20bc5-1214-465a-bc35-c75a4dd6851f","XPosition":-15,"YPosition":-4,"TileSetNumber":7,"TileAtlasCoOrdinateX":0,"TileAtlasCoOrdinateY":0,"Layer":0,"IsInZone":false,"WallId":"string","Walkable":true,"ExhibitId":"string","HangingLightId":"string"},{"Id":"5eff90b1-c472-47e6-943d-cde9a027bdaf","XPosition":-15,"YPosition":-5,"TileSetNumber":7,"TileAtlasCoOrdinateX":0,"TileAtlasCoOrdinateY":0,"Layer":0,"IsInZone":false,"WallId":"string","Walkable":true,"ExhibitId":"string","HangingLightId":"string"},{"Id":"a662ed3f-d12c-461e-8707-22118d74ddf8","XPosition":-15,"YPosition":-6,"TileSetNumber":7,"TileAtlasCoOrdinateX":0,"TileAtlasCoOrdinateY":0,"Layer":0,"IsInZone":false,"WallId":"string","Walkable":true,"ExhibitId":"string","HangingLightId":"string"},{"Id":"d07e0130-8427-47af-8a66-526e6f174431","XPosition":-15,"YPosition":-7,"TileSetNumber":7,"TileAtlasCoOrdinateX":0,"TileAtlasCoOrdinateY":0,"Layer":0,"IsInZone":false,"WallId":"string","Walkable":true,"ExhibitId":"string","HangingLightId":"string"},{"Id":"7ba9a61d-b57b-4588-b6e0-0d37afbfcc56","XPosition":-15,"YPosition":-8,"TileSetNumber":7,"TileAtlasCoOrdinateX":0,"TileAtlasCoOrdinateY":0,"Layer":0,"IsInZone":false,"WallId":"string","Walkable":true,"ExhibitId":"string","HangingLightId":"string"},{"Id":"9de2a9f1-4f33-403e-99ad-61a8b74d261e","XPosition":-15,"YPosition":-9,"TileSetNumber":7,"TileAtlasCoOrdinateX":0,"TileAtlasCoOrdinateY":0,"Layer":0,"IsInZone":false,"WallId":"string","Walkable":true,"ExhibitId":"string","HangingLightId":"string"},{"Id":"751f0d86-5c9d-4f5d-a2e0-9015bf4ff1de","XPosition":-15,"YPosition":-10,"TileSetNumber":7,"TileAtlasCoOrdinateX":0,"TileAtlasCoOrdinateY":0,"Layer":0,"IsInZone":false,"WallId":"string","Walkable":true,"ExhibitId":"string","HangingLightId":"string"},{"Id":"ad96f93f-50dc-4831-ae3b-d996e48c7d5b","XPosition":-15,"YPosition":-11,"TileSetNumber":7,"TileAtlasCoOrdinateX":0,"TileAtlasCoOrdinateY":0,"Layer":0,"IsInZone":false,"WallId":"string","Walkable":true,"ExhibitId":"string","HangingLightId":"string"},{"Id":"c2e2f712-71cf-4928-aebb-6d81aef78d15","XPosition":-15,"YPosition":-12,"TileSetNumber":7,"TileAtlasCoOrdinateX":0,"TileAtlasCoOrdinateY":0,"Layer":0,"IsInZone":false,"WallId":"string","Walkable":true,"ExhibitId":"string","HangingLightId":"string"},{"Id":"0d31e84c-41e7-453f-9555-75212e441801","XPosition":-15,"YPosition":-13,"TileSetNumber":7,"TileAtlasCoOrdinateX":0,"TileAtlasCoOrdinateY":0,"Layer":0,"IsInZone":false,"WallId":"string","Walkable":true,"ExhibitId":"string","HangingLightId":"string"},{"Id":"dffd0b07-5780-4a87-a117-14d217c03acd","XPosition":-15,"YPosition":-14,"TileSetNumber":7,"TileAtlasCoOrdinateX":0,"TileAtlasCoOrdinateY":0,"Layer":0,"IsInZone":false,"WallId":"string","Walkable":true,"ExhibitId":"string","HangingLightId":"string"},{"Id":"f4979d77-2608-4107-a8bd-b73908a4978e","XPosition":-15,"YPosition":-15,"TileSetNumber":7,"TileAtlasCoOrdinateX":0,"TileAtlasCoOrdinateY":0,"Layer":0,"IsInZone":false,"WallId":"string","Walkable":true,"ExhibitId":"string","HangingLightId":"string"},{"Id":"ee3dc91b-4ef6-4611-b9ef-f7691a29d6b9","XPosition":-15,"YPosition":-16,"TileSetNumber":7,"TileAtlasCoOrdinateX":0,"TileAtlasCoOrdinateY":0,"Layer":0,"IsInZone":false,"WallId":"string","Walkable":true,"ExhibitId":"string","HangingLightId":"string"},{"Id":"1cdd47d3-b4bb-4f3d-8019-4c0d2bb180d2","XPosition":-15,"YPosition":-17,"TileSetNumber":7,"TileAtlasCoOrdinateX":0,"TileAtlasCoOrdinateY":0,"Layer":0,"IsInZone":false,"WallId":"string","Walkable":true,"ExhibitId":"string","HangingLightId":"string"},{"Id":"5dd61b37-58f3-4c5d-98fa-e45159b12369","XPosition":-15,"YPosition":-18,"TileSetNumber":7,"TileAtlasCoOrdinateX":0,"TileAtlasCoOrdinateY":0,"Layer":0,"IsInZone":false,"WallId":"string","Walkable":true,"ExhibitId":"string","HangingLightId":"string"},{"Id":"8f96b791-d060-4e24-aff9-3e74508fc566","XPosition":-15,"YPosition":-19,"TileSetNumber":7,"TileAtlasCoOrdinateX":0,"TileAtlasCoOrdinateY":0,"Layer":0,"IsInZone":false,"WallId":"basic_red_wallpaper","Walkable":true,"ExhibitId":"string","HangingLightId":"string"},{"Id":"aa514ed2-efe2-4cbd-b28e-4b9673363360","XPosition":-16,"YPosition":0,"TileSetNumber":7,"TileAtlasCoOrdinateX":0,"TileAtlasCoOrdinateY":0,"Layer":0,"IsInZone":false,"WallId":"string","Walkable":false,"ExhibitId":"string","HangingLightId":"string"},{"Id":"eebb2a2e-d79e-4afe-9323-5fc9745e1d56","XPosition":-16,"YPosition":-1,"TileSetNumber":7,"TileAtlasCoOrdinateX":0,"TileAtlasCoOrdinateY":0,"Layer":0,"IsInZone":false,"WallId":"string","Walkable":true,"ExhibitId":"string","HangingLightId":"string"},{"Id":"45c8f024-dbfe-4ed2-954b-a0738a16c424","XPosition":-16,"YPosition":-2,"TileSetNumber":7,"TileAtlasCoOrdinateX":0,"TileAtlasCoOrdinateY":0,"Layer":0,"IsInZone":false,"WallId":"string","Walkable":true,"ExhibitId":"string","HangingLightId":"string"},{"Id":"47dc2621-1b32-4332-aef6-e1d7c2236c0f","XPosition":-16,"YPosition":-3,"TileSetNumber":7,"TileAtlasCoOrdinateX":0,"TileAtlasCoOrdinateY":0,"Layer":0,"IsInZone":false,"WallId":"string","Walkable":true,"ExhibitId":"string","HangingLightId":"string"},{"Id":"ae5f0f5d-fe1c-4638-a6c1-ebbf090b5cf5","XPosition":-16,"YPosition":-4,"TileSetNumber":7,"TileAtlasCoOrdinateX":0,"TileAtlasCoOrdinateY":0,"Layer":0,"IsInZone":false,"WallId":"string","Walkable":true,"ExhibitId":"string","HangingLightId":"string"},{"Id":"5dea8fc6-5952-4593-8bdf-b0f4c7bf37c5","XPosition":-16,"YPosition":-5,"TileSetNumber":7,"TileAtlasCoOrdinateX":0,"TileAtlasCoOrdinateY":0,"Layer":0,"IsInZone":false,"WallId":"string","Walkable":true,"ExhibitId":"string","HangingLightId":"string"},{"Id":"482a7d77-bf51-45ad-874a-6ac6c7469b6f","XPosition":-16,"YPosition":-6,"TileSetNumber":7,"TileAtlasCoOrdinateX":0,"TileAtlasCoOrdinateY":0,"Layer":0,"IsInZone":false,"WallId":"string","Walkable":true,"ExhibitId":"string","HangingLightId":"string"},{"Id":"5589bd1b-e07a-4f94-bb19-39458d176e1a","XPosition":-16,"YPosition":-7,"TileSetNumber":7,"TileAtlasCoOrdinateX":0,"TileAtlasCoOrdinateY":0,"Layer":0,"IsInZone":false,"WallId":"string","Walkable":true,"ExhibitId":"string","HangingLightId":"string"},{"Id":"7b7bbe6f-40ef-42e1-9ef0-4997e269c7b8","XPosition":-16,"YPosition":-8,"TileSetNumber":7,"TileAtlasCoOrdinateX":0,"TileAtlasCoOrdinateY":0,"Layer":0,"IsInZone":false,"WallId":"string","Walkable":true,"ExhibitId":"string","HangingLightId":"string"},{"Id":"3b12dec0-4684-4642-b76a-e3897dbe5ff7","XPosition":-16,"YPosition":-9,"TileSetNumber":7,"TileAtlasCoOrdinateX":0,"TileAtlasCoOrdinateY":0,"Layer":0,"IsInZone":false,"WallId":"string","Walkable":true,"ExhibitId":"string","HangingLightId":"string"},{"Id":"b6191a44-e372-4aae-8c37-42165d9427a8","XPosition":-16,"YPosition":-10,"TileSetNumber":7,"TileAtlasCoOrdinateX":0,"TileAtlasCoOrdinateY":0,"Layer":0,"IsInZone":false,"WallId":"string","Walkable":true,"ExhibitId":"string","HangingLightId":"string"},{"Id":"cc11e6fe-b184-45a1-b61f-6178c3e6396e","XPosition":-16,"YPosition":-11,"TileSetNumber":7,"TileAtlasCoOrdinateX":0,"TileAtlasCoOrdinateY":0,"Layer":0,"IsInZone":false,"WallId":"string","Walkable":true,"ExhibitId":"string","HangingLightId":"string"},{"Id":"10b044e9-e67b-4652-94ec-1568e7b8e5db","XPosition":-16,"YPosition":-12,"TileSetNumber":7,"TileAtlasCoOrdinateX":0,"TileAtlasCoOrdinateY":0,"Layer":0,"IsInZone":false,"WallId":"string","Walkable":false,"ExhibitId":"d99ff900-1e8c-4219-946c-34301a12bd7c","HangingLightId":"string"},{"Id":"25105223-e582-48ae-8b8c-7b43ef0c91f1","XPosition":-16,"YPosition":-13,"TileSetNumber":7,"TileAtlasCoOrdinateX":0,"TileAtlasCoOrdinateY":0,"Layer":0,"IsInZone":false,"WallId":"string","Walkable":true,"ExhibitId":"string","HangingLightId":"string"},{"Id":"3a31e087-7910-43ae-9060-9675aaa3e714","XPosition":-16,"YPosition":-14,"TileSetNumber":7,"TileAtlasCoOrdinateX":0,"TileAtlasCoOrdinateY":0,"Layer":0,"IsInZone":false,"WallId":"string","Walkable":true,"ExhibitId":"string","HangingLightId":"string"},{"Id":"4a6fe892-2ba8-4935-9d92-fda5f1a3fba1","XPosition":-16,"YPosition":-15,"TileSetNumber":7,"TileAtlasCoOrdinateX":0,"TileAtlasCoOrdinateY":0,"Layer":0,"IsInZone":false,"WallId":"string","Walkable":true,"ExhibitId":"string","HangingLightId":"string"},{"Id":"89e5574a-4003-4648-8ab0-ef3c3defe348","XPosition":-16,"YPosition":-16,"TileSetNumber":7,"TileAtlasCoOrdinateX":0,"TileAtlasCoOrdinateY":0,"Layer":0,"IsInZone":false,"WallId":"string","Walkable":true,"ExhibitId":"string","HangingLightId":"string"},{"Id":"ca914801-5712-491a-8520-5936ee710f92","XPosition":-16,"YPosition":-17,"TileSetNumber":7,"TileAtlasCoOrdinateX":0,"TileAtlasCoOrdinateY":0,"Layer":0,"IsInZone":false,"WallId":"string","Walkable":true,"ExhibitId":"string","HangingLightId":"string"},{"Id":"781a052f-25e8-419f-9cc4-45cee82c0398","XPosition":-16,"YPosition":-18,"TileSetNumber":7,"TileAtlasCoOrdinateX":0,"TileAtlasCoOrdinateY":0,"Layer":0,"IsInZone":false,"WallId":"string","Walkable":true,"ExhibitId":"string","HangingLightId":"string"},{"Id":"8c61bed0-867c-4c86-9cde-1b95a421273c","XPosition":-16,"YPosition":-19,"TileSetNumber":7,"TileAtlasCoOrdinateX":0,"TileAtlasCoOrdinateY":0,"Layer":0,"IsInZone":false,"WallId":"basic_red_wallpaper","Walkable":true,"ExhibitId":"string","HangingLightId":"string"},{"Id":"f6150243-7678-4650-862c-9ad685324268","XPosition":-17,"YPosition":0,"TileSetNumber":7,"TileAtlasCoOrdinateX":0,"TileAtlasCoOrdinateY":0,"Layer":0,"IsInZone":false,"WallId":"basic_red_wallpaper","Walkable":false,"ExhibitId":"string","HangingLightId":"string"},{"Id":"1d1f8f87-d0a8-4e31-ac14-e830b6821ccd","XPosition":-17,"YPosition":-1,"TileSetNumber":7,"TileAtlasCoOrdinateX":0,"TileAtlasCoOrdinateY":0,"Layer":0,"IsInZone":false,"WallId":"basic_red_wallpaper","Walkable":true,"ExhibitId":"string","HangingLightId":"string"},{"Id":"e8b41e87-8f56-470e-b9ff-a14b2cb30e7e","XPosition":-17,"YPosition":-2,"TileSetNumber":7,"TileAtlasCoOrdinateX":0,"TileAtlasCoOrdinateY":0,"Layer":0,"IsInZone":false,"WallId":"basic_red_wallpaper","Walkable":true,"ExhibitId":"string","HangingLightId":"string"},{"Id":"17402e31-8a32-481e-a249-d6cdb9fef8fd","XPosition":-17,"YPosition":-3,"TileSetNumber":7,"TileAtlasCoOrdinateX":0,"TileAtlasCoOrdinateY":0,"Layer":0,"IsInZone":false,"WallId":"basic_red_wallpaper","Walkable":true,"ExhibitId":"string","HangingLightId":"string"},{"Id":"f4797da1-a30e-4501-8f84-84a32513cc50","XPosition":-17,"YPosition":-4,"TileSetNumber":7,"TileAtlasCoOrdinateX":0,"TileAtlasCoOrdinateY":0,"Layer":0,"IsInZone":false,"WallId":"basic_red_wallpaper","Walkable":false,"ExhibitId":"a3593d27-2ded-4535-b775-9f02e683c1cd","HangingLightId":"string"},{"Id":"75b8e496-08df-468c-b25f-e1557efe8c54","XPosition":-17,"YPosition":-5,"TileSetNumber":7,"TileAtlasCoOrdinateX":0,"TileAtlasCoOrdinateY":0,"Layer":0,"IsInZone":false,"WallId":"basic_red_wallpaper","Walkable":true,"ExhibitId":"string","HangingLightId":"string"},{"Id":"6aba8db3-a0e2-4565-bf84-52432740da42","XPosition":-17,"YPosition":-6,"TileSetNumber":7,"TileAtlasCoOrdinateX":0,"TileAtlasCoOrdinateY":0,"Layer":0,"IsInZone":false,"WallId":"basic_red_wallpaper","Walkable":true,"ExhibitId":"string","HangingLightId":"string"},{"Id":"1888b089-190f-460e-8fa4-386a84cb33e7","XPosition":-17,"YPosition":-7,"TileSetNumber":7,"TileAtlasCoOrdinateX":0,"TileAtlasCoOrdinateY":0,"Layer":0,"IsInZone":false,"WallId":"basic_red_wallpaper","Walkable":true,"ExhibitId":"string","HangingLightId":"string"},{"Id":"4a5c68c5-9253-450b-8996-0c0c0e17be51","XPosition":-17,"YPosition":-8,"TileSetNumber":7,"TileAtlasCoOrdinateX":0,"TileAtlasCoOrdinateY":0,"Layer":0,"IsInZone":false,"WallId":"basic_red_wallpaper","Walkable":true,"ExhibitId":"string","HangingLightId":"string"},{"Id":"34ba02fe-644a-4362-ae8a-e19e0473981a","XPosition":-17,"YPosition":-9,"TileSetNumber":7,"TileAtlasCoOrdinateX":0,"TileAtlasCoOrdinateY":0,"Layer":0,"IsInZone":false,"WallId":"basic_red_wallpaper","Walkable":true,"ExhibitId":"string","HangingLightId":"string"},{"Id":"ef3c74f5-1ea8-4e77-8f17-dc9669c6a507","XPosition":-17,"YPosition":-10,"TileSetNumber":7,"TileAtlasCoOrdinateX":0,"TileAtlasCoOrdinateY":0,"Layer":0,"IsInZone":false,"WallId":"basic_red_wallpaper","Walkable":true,"ExhibitId":"string","HangingLightId":"string"},{"Id":"4d74543f-a247-46a5-bd11-d9069bd641f6","XPosition":-17,"YPosition":-11,"TileSetNumber":7,"TileAtlasCoOrdinateX":0,"TileAtlasCoOrdinateY":0,"Layer":0,"IsInZone":false,"WallId":"basic_red_wallpaper","Walkable":true,"ExhibitId":"string","HangingLightId":"string"},{"Id":"36ade91b-0aae-4065-921c-f8ad56a7c3c9","XPosition":-17,"YPosition":-12,"TileSetNumber":7,"TileAtlasCoOrdinateX":0,"TileAtlasCoOrdinateY":0,"Layer":0,"IsInZone":false,"WallId":"basic_red_wallpaper","Walkable":true,"ExhibitId":"string","HangingLightId":"string"},{"Id":"4f78b33c-53b9-4967-b8ee-c82cd7672a41","XPosition":-17,"YPosition":-13,"TileSetNumber":7,"TileAtlasCoOrdinateX":0,"TileAtlasCoOrdinateY":0,"Layer":0,"IsInZone":false,"WallId":"basic_red_wallpaper","Walkable":true,"ExhibitId":"string","HangingLightId":"string"},{"Id":"1076662b-b9e9-48bf-8b12-aa202347fb31","XPosition":-17,"YPosition":-14,"TileSetNumber":7,"TileAtlasCoOrdinateX":0,"TileAtlasCoOrdinateY":0,"Layer":0,"IsInZone":false,"WallId":"basic_red_wallpaper","Walkable":true,"ExhibitId":"string","HangingLightId":"string"},{"Id":"f158508e-f5f1-4428-8edc-e52953d5b230","XPosition":-17,"YPosition":-15,"TileSetNumber":7,"TileAtlasCoOrdinateX":0,"TileAtlasCoOrdinateY":0,"Layer":0,"IsInZone":false,"WallId":"basic_red_wallpaper","Walkable":true,"ExhibitId":"string","HangingLightId":"string"},{"Id":"8fe8abea-cb1c-410e-9576-e32c9d883cd0","XPosition":-17,"YPosition":-16,"TileSetNumber":7,"TileAtlasCoOrdinateX":0,"TileAtlasCoOrdinateY":0,"Layer":0,"IsInZone":false,"WallId":"basic_red_wallpaper","Walkable":true,"ExhibitId":"string","HangingLightId":"string"},{"Id":"956ecf5e-4ce0-4909-b425-bfe888a5b068","XPosition":-17,"YPosition":-17,"TileSetNumber":7,"TileAtlasCoOrdinateX":0,"TileAtlasCoOrdinateY":0,"Layer":0,"IsInZone":false,"WallId":"basic_red_wallpaper","Walkable":true,"ExhibitId":"string","HangingLightId":"string"},{"Id":"36e6d4cf-2400-47cc-af7b-c817b7865dc0","XPosition":-17,"YPosition":-18,"TileSetNumber":7,"TileAtlasCoOrdinateX":0,"TileAtlasCoOrdinateY":0,"Layer":0,"IsInZone":false,"WallId":"basic_red_wallpaper","Walkable":true,"ExhibitId":"string","HangingLightId":"string"},{"Id":"b54ad2f0-d293-4fbf-b2b2-89e1e1717de0","XPosition":-17,"YPosition":-19,"TileSetNumber":7,"TileAtlasCoOrdinateX":0,"TileAtlasCoOrdinateY":0,"Layer":0,"IsInZone":false,"WallId":"basic_red_wallpaper","Walkable":true,"ExhibitId":"string","HangingLightId":"string"}]